Workbook

Sheet Notes
A1: Workforce Cost Variance Model — Notes & Methodology
A4: Scope | B4: 4 locations x 26 positions (Workforce Data, Transaction Data tabs).
A5: Scenario definitions
A6: Plan | B6: Original 2026 budget, set once at start of year.
A7: Prior Forecast | B7: Most recent 2026 re-forecast before the current one.
A8: Current Forecast | B8: Latest 2026 re-forecast (this model's "forecast" for variance purposes).
A9: Actual | B9: Only available for 2025 (last closed year). No 2026 actual exists yet in source data.
A11: Variance methodology
A12: Budget variance | B12: Current Forecast minus Plan. Negative = under budget (favorable). Positive = over budget (unfavorable).
A13: Re-forecast drift | B13: Current Forecast minus Prior Forecast. Shows whether the latest view is trending up or down vs the prior update.
A15: Efficiency methodology
A16: Primary ratio | B16: Labor $ per rental transaction, using 2025 Actual labor cost / 2025 Actual transactions (clean, both-actual basis).
A17: Secondary ratio | B17: 2026 Plan labor cost / 2026 Plan transactions, compared to the 2025 actual ratio to see if the budget assumes efficiency improves or erodes.

Sheet Location Summary
A5: Location | B5: FTE Current Forecast | C5: FTE Plan | D5: Labor $ Current Forecast | E5: Labor $ Plan | F5: Labor $ Prior Forecast
A6: Location 1 | B6: =SUMIF('Raw - Workforce'!$A$2:$A$105,A6,'Raw - Workforce'!$C$2:$C$105) -> 2271.6522 | C6: =SUMIF('Raw - Workforce'!$A$2:$A$105,A6,'Raw - Workforce'!$E$2:$E$105) -> 2417.9278 | D6: =SUMIF('Variance Analysis'!$A$2:$A$105,A6,'Variance Analysis'!$C$2:$C$105) -> 9574757.3 | E6: =SUMIF('Variance Analysis'!$A$2:$A$105,A6,'Variance Analysis'!$E$2:$E$105) -> 9859466.6 | F6: =SUMIF('Variance Analysis'!$A$2:$A$105,A6,'Variance Analysis'!$D$2:$D$105) -> 9656878.7
A7: Location 2 | B7: =SUMIF('Raw - Workforce'!$A$2:$A$105,A7,'Raw - Workforce'!$C$2:$C$105) -> 2379.988 | C7: =SUMIF('Raw - Workforce'!$A$2:$A$105,A7,'Raw - Workforce'!$E$2:$E$105) -> 2526.5351 | D7: =SUMIF('Variance Analysis'!$A$2:$A$105,A7,'Variance Analysis'!$C$2:$C$105) -> 8196137.9 | E7: =SUMIF('Variance Analysis'!$A$2:$A$105,A7,'Variance Analysis'!$E$2:$E$105) -> 8419827.5 | F7: =SUMIF('Variance Analysis'!$A$2:$A$105,A7,'Variance Analysis'!$D$2:$D$105) -> 8046167.5
A8: Location 3 | B8: =SUMIF('Raw - Workforce'!$A$2:$A$105,A8,'Raw - Workforce'!$C$2:$C$105) -> 2804.4606 | C8: =SUMIF('Raw - Workforce'!$A$2:$A$105,A8,'Raw - Workforce'!$E$2:$E$105) -> 2817.3301 | D8: =SUMIF('Variance Analysis'!$A$2:$A$105,A8,'Variance Analysis'!$C$2:$C$105) -> 10714422 | E8: =SUMIF('Variance Analysis'!$A$2:$A$105,A8,'Variance Analysis'!$E$2:$E$105) -> 10741859 | F8: =SUMIF('Variance Analysis'!$A$2:$A$105,A8,'Variance Analysis'!$D$2:$D$105) -> 10493876
A9: Location 4 | B9: =SUMIF('Raw - Workforce'!$A$2:$A$105,A9,'Raw - Workforce'!$C$2:$C$105) -> 3252.266 | C9: =SUMIF('Raw - Workforce'!$A$2:$A$105,A9,'Raw - Workforce'!$E$2:$E$105) -> 3455.8254 | D9: =SUMIF('Variance Analysis'!$A$2:$A$105,A9,'Variance Analysis'!$C$2:$C$105) -> 15038965 | E9: =SUMIF('Variance Analysis'!$A$2:$A$105,A9,'Variance Analysis'!$E$2:$E$105) -> 15368664 | F9: =SUMIF('Variance Analysis'!$A$2:$A$105,A9,'Variance Analysis'!$D$2:$D$105) -> 15035566
A10: Company Total | B10: =SUM(B6:B9) -> 10708.367 | C10: =SUM(C6:C9) -> 11217.618 | D10: =SUM(D6:D9) -> 43524282 | E10: =SUM(E6:E9) -> 44389818 | F10: =SUM(F6:F9) -> 43232489
A15: Location | B15: Var $ vs Plan | C15: Var % vs Plan | D15: Var $ vs Prior Forecast | E15: Var % vs Prior Forecast | F15: OT % of Salary Actual 2025 | G15: OT % of Salary Plan | H15: OT % of Salary Current Forecast
A16: Location 1 | B16: =D6-E6 -> -284709.23 | C16: =IFERROR(B16/E6,0) -> -0.028876738 | D16: =D6-F6 -> -82121.345 | E16: (.85%) | F16: =IFERROR(SUMIF('Raw - Workforce'!$A$2:$A$105,A6,'Raw - Workforce'!$N$2:$N$105)/SUMIF('Raw - Workforce'!$A$2:$A$105,A6,'Raw - Workforce'!$J$2:$J$105),0) -> 0.16532266 | G16: =IFERROR(SUMIF('Raw - Workforce'!$A$2:$A$105,A6,'Raw - Workforce'!$M$2:$M$105)/SUMIF('Raw - Workforce'!$A$2:$A$105,A6,'Raw - Workforce'!$I$2:$I$105),0) -> 0.14917003 | H16: =IFERROR(SUMIF('Raw - Workforce'!$A$2:$A$105,A6,'Raw - Workforce'!$K$2:$K$105)/SUMIF('Raw - Workforce'!$A$2:$A$105,A6,'Raw - Workforce'!$G$2:$G$105),0) -> 0.12452456
A17: Location 2 | B17: =D7-E7 -> -223689.51 | C17: =IFERROR(B17/E7,0) -> -0.026566994 | D17: =D7-F7 -> 149970.48 | E17: =D17/F7 -> 0.018638747 | F17: =IFERROR(SUMIF('Raw - Workforce'!$A$2:$A$105,A7,'Raw - Workforce'!$N$2:$N$105)/SUMIF('Raw - Workforce'!$A$2:$A$105,A7,'Raw - Workforce'!$J$2:$J$105),0) -> 0.10011764 | G17: =IFERROR(SUMIF('Raw - Workforce'!$A$2:$A$105,A7,'Raw - Workforce'!$M$2:$M$105)/SUMIF('Raw - Workforce'!$A$2:$A$105,A7,'Raw - Workforce'!$I$2:$I$105),0) -> 0.078056723 | H17: =IFERROR(SUMIF('Raw - Workforce'!$A$2:$A$105,A7,'Raw - Workforce'!$K$2:$K$105)/SUMIF('Raw - Workforce'!$A$2:$A$105,A7,'Raw - Workforce'!$G$2:$G$105),0) -> 0.077564782
A18: Location 3 | B18: =D8-E8 -> -27437.755 | C18: =IFERROR(B18/E8,0) -> -0.0025542836 | D18: =D8-F8 -> 220545.33 | E18: =D18/F8 -> 0.021016574 | F18: =IFERROR(SUMIF('Raw - Workforce'!$A$2:$A$105,A8,'Raw - Workforce'!$N$2:$N$105)/SUMIF('Raw - Workforce'!$A$2:$A$105,A8,'Raw - Workforce'!$J$2:$J$105),0) -> 0.11472845 | G18: =IFERROR(SUMIF('Raw - Workforce'!$A$2:$A$105,A8,'Raw - Workforce'!$M$2:$M$105)/SUMIF('Raw - Workforce'!$A$2:$A$105,A8,'Raw - Workforce'!$I$2:$I$105),0) -> 0.090821841 | H18: =IFERROR(SUMIF('Raw - Workforce'!$A$2:$A$105,A8,'Raw - Workforce'!$K$2:$K$105)/SUMIF('Raw - Workforce'!$A$2:$A$105,A8,'Raw - Workforce'!$G$2:$G$105),0) -> 0.085183002
A19: Location 4 | B19: =D9-E9 -> -329699.64 | C19: =IFERROR(B19/E9,0) -> -0.021452719 | D19: =D9-F9 -> 3398.46 | E19: =D19/F9 -> 0.00022602807 | F19: =IFERROR(SUMIF('Raw - Workforce'!$A$2:$A$105,A9,'Raw - Workforce'!$N$2:$N$105)/SUMIF('Raw - Workforce'!$A$2:$A$105,A9,'Raw - Workforce'!$J$2:$J$105),0) -> 0.10584733 | G19: =IFERROR(SUMIF('Raw - Workforce'!$A$2:$A$105,A9,'Raw - Workforce'!$M$2:$M$105)/SUMIF('Raw - Workforce'!$A$2:$A$105,A9,'Raw - Workforce'!$I$2:$I$105),0) -> 0.094684516 | H19: =IFERROR(SUMIF('Raw - Workforce'!$A$2:$A$105,A9,'Raw - Workforce'!$K$2:$K$105)/SUMIF('Raw - Workforce'!$A$2:$A$105,A9,'Raw - Workforce'!$G$2:$G$105),0) -> 0.086024099
A20: Company Total | B20: =SUM(B16:B19) -> -865536.13 | C20: =IFERROR(B20/E10,0) -> -0.019498529 | D20: =SUM(D16:D19) -> 291792.92 | E20: =IFERROR(D20/F10,0) -> 0.0067493898 | F20: =SUM('Raw - Workforce'!$N$2:$N$105)/SUM('Raw - Workforce'!$J$2:$J$105) -> 0.11935619 | G20: =SUM('Raw - Workforce'!$M$2:$M$105)/SUM('Raw - Workforce'!$I$2:$I$105) -> 0.10212213 | H20: =SUM('Raw - Workforce'!$K$2:$K$105)/SUM('Raw - Workforce'!$G$2:$G$105) -> 0.092428546

Sheet Efficiency Metrics
A2: Labor = Salary + Overtime = Total Labor Cost before benefits.
A5: Location | B5: Labor $ Actual 2025 | C5: Rental Transactions Actual 2025 | D5: Labor $/Transactions Actual 2025 (clean baseline) | E5: Labor $ Plan 2026 | F5: Rental Transactions Plan 2026 | G5: Labor $/Transactions Plan 2026
A6: ='Location Summary'!A6 -> Location 1 | B6: =SUMIF('Variance Analysis'!$A$2:$A$105,A6,'Variance Analysis'!$F$2:$F$105) -> 9144531.1 | C6: =INDEX('Raw - Transactions'!$E$2:$E$5,MATCH(A6,'Raw - Transactions'!$A$2:$A$5,0)) -> 402999 | D6: =IFERROR(B6/C6,0) -> 22.6912 | E6: ='Location Summary'!E6 -> 9859466.6 | F6: =INDEX('Raw - Transactions'!$D$2:$D$5,MATCH(A6,'Raw - Transactions'!$A$2:$A$5,0)) -> 425982.47 | G6: =IFERROR(E6/F6,0) -> 23.14524
A7: ='Location Summary'!A7 -> Location 2 | B7: =SUMIF('Variance Analysis'!$A$2:$A$105,A7,'Variance Analysis'!$F$2:$F$105) -> 7866269 | C7: =INDEX('Raw - Transactions'!$E$2:$E$5,MATCH(A7,'Raw - Transactions'!$A$2:$A$5,0)) -> 593382 | D7: =IFERROR(B7/C7,0) -> 13.256669 | E7: ='Location Summary'!E7 -> 8419827.5 | F7: =INDEX('Raw - Transactions'!$D$2:$D$5,MATCH(A7,'Raw - Transactions'!$A$2:$A$5,0)) -> 599083.3 | G7: =IFERROR(E7/F7,0) -> 14.054519
A8: ='Location Summary'!A8 -> Location 3 | B8: =SUMIF('Variance Analysis'!$A$2:$A$105,A8,'Variance Analysis'!$F$2:$F$105) -> 10464226 | C8: =INDEX('Raw - Transactions'!$E$2:$E$5,MATCH(A8,'Raw - Transactions'!$A$2:$A$5,0)) -> 602273 | D8: =IFERROR(B8/C8,0) -> 17.374557 | E8: ='Location Summary'!E8 -> 10741859 | F8: =INDEX('Raw - Transactions'!$D$2:$D$5,MATCH(A8,'Raw - Transactions'!$A$2:$A$5,0)) -> 625480.95 | G8: =IFERROR(E8/F8,0) -> 17.17376
A9: ='Location Summary'!A9 -> Location 4 | B9: =SUMIF('Variance Analysis'!$A$2:$A$105,A9,'Variance Analysis'!$F$2:$F$105) -> 14710693 | C9: =INDEX('Raw - Transactions'!$E$2:$E$5,MATCH(A9,'Raw - Transactions'!$A$2:$A$5,0)) -> 606371 | D9: =IFERROR(B9/C9,0) -> 24.260219 | E9: ='Location Summary'!E9 -> 15368664 | F9: =INDEX('Raw - Transactions'!$D$2:$D$5,MATCH(A9,'Raw - Transactions'!$A$2:$A$5,0)) -> 629076.38 | G9: =IFERROR(E9/F9,0) -> 24.430522
A10: Company Total | B10: =SUM(B6:B9) -> 42185720 | C10: =SUM(C6:C9) -> 2205025 | D10: =IFERROR(B10/C10,0) -> 19.131629 | E10: =SUM(E6:E9) -> 44389818 | F10: =SUM(F6:F9) -> 2279623.1 | G10: =IFERROR(E10/F10,0) -> 19.472437

Sheet Top Movers
A9: Top 8 Favorable (largest cost savings vs Plan)
A10: Location | B10: Position | C10: Labor $ Current Forecast | D10: Labor $ Plan | E10: Var $ vs Plan | F10: FTE Var vs Plan
A11: ='[1]Variance Analysis'!A55 -> Location 3 | B11: ='[1]Variance Analysis'!B55 -> Position B | C11: ='[1]Variance Analysis'!C55 -> 1445020.5 | D11: ='[1]Variance Analysis'!E55 -> 1706992.9 | E11: ='[1]Variance Analysis'!G55 -> -261972.36 | F11: ='[1]Variance Analysis'!J55 -> -82.074351
A12: ='[1]Variance Analysis'!A61 -> Location 3 | B12: ='[1]Variance Analysis'!B61 -> Position H | C12: ='[1]Variance Analysis'!C61 -> 1252895 | D12: ='[1]Variance Analysis'!E61 -> 1457336.4 | E12: ='[1]Variance Analysis'!G61 -> -204441.42 | F12: ='[1]Variance Analysis'!J61 -> -43.626628
A13: ='[1]Variance Analysis'!A29 -> Location 2 | B13: ='[1]Variance Analysis'!B29 -> Position B | C13: ='[1]Variance Analysis'!C29 -> 1314928.6 | D13: ='[1]Variance Analysis'!E29 -> 1507894.1 | E13: ='[1]Variance Analysis'!G29 -> -192965.41 | F13: ='[1]Variance Analysis'!J29 -> -65.99
A14: ='[1]Variance Analysis'!A80 -> Location 4 | B14: ='[1]Variance Analysis'!B80 -> Position A | C14: ='[1]Variance Analysis'!C80 -> 1560596.1 | D14: ='[1]Variance Analysis'!E80 -> 1735596.1 | E14: ='[1]Variance Analysis'!G80 -> -175000 | F14: ='[1]Variance Analysis'!J80 -> -60
A15: ='[1]Variance Analysis'!A54 -> Location 3 | B15: ='[1]Variance Analysis'!B54 -> Position A | C15: ='[1]Variance Analysis'!C54 -> 889662.46 | D15: ='[1]Variance Analysis'!E54 -> 1055190.3 | E15: ='[1]Variance Analysis'!G54 -> -165527.81 | F15: ='[1]Variance Analysis'!J54 -> -53.576846
A16: ='[1]Variance Analysis'!A81 -> Location 4 | B16: ='[1]Variance Analysis'!B81 -> Position B | C16: ='[1]Variance Analysis'!C81 -> 2467569.9 | D16: ='[1]Variance Analysis'!E81 -> 2613599.1 | E16: ='[1]Variance Analysis'!G81 -> -146029.16 | F16: ='[1]Variance Analysis'!J81 -> -62.9
A17: ='[1]Variance Analysis'!A6 -> Location 1 | B17: ='[1]Variance Analysis'!B6 -> Position E | C17: ='[1]Variance Analysis'!C6 -> 116986.9 | D17: ='[1]Variance Analysis'!E6 -> 248284.51 | E17: ='[1]Variance Analysis'!G6 -> -131297.61 | F17: ='[1]Variance Analysis'!J6 -> -24.456722
A18: ='[1]Variance Analysis'!A22 -> Location 1 | B18: ='[1]Variance Analysis'!B22 -> Position U | C18: ='[1]Variance Analysis'!C22 -> 188589.42 | D18: ='[1]Variance Analysis'!E22 -> 301888.72 | E18: ='[1]Variance Analysis'!G22 -> -113299.29 | F18: ='[1]Variance Analysis'!J22 -> 1
A20: Top 8 Unfavorable (largest cost overruns vs Plan)
A21: Location | B21: Position | C21: Labor $ Current Forecast | D21: Labor $ Plan | E21: Var $ vs Plan | F21: FTE Var vs Plan
A22: ='[1]Variance Analysis'!A64 -> Location 3 | B22: ='[1]Variance Analysis'!B64 -> Position K | C22: ='[1]Variance Analysis'!C64 -> 1274717 | D22: ='[1]Variance Analysis'!E64 -> 857934.8 | E22: ='[1]Variance Analysis'!G64 -> 416782.18 | F22: ='[1]Variance Analysis'!J64 -> 124.79767
A23: ='[1]Variance Analysis'!A25 -> Location 1 | B23: ='[1]Variance Analysis'!B25 -> Position X | C23: ='[1]Variance Analysis'!C25 -> 1180430.1 | D23: ='[1]Variance Analysis'!E25 -> 891350.78 | E23: ='[1]Variance Analysis'!G25 -> 289079.32 | F23: ='[1]Variance Analysis'!J25 -> 2
A24: ='[1]Variance Analysis'!A65 -> Location 3 | B24: ='[1]Variance Analysis'!B65 -> Position L | C24: ='[1]Variance Analysis'!C65 -> 356485.13 | D24: ='[1]Variance Analysis'!E65 -> 164226.05 | E24: ='[1]Variance Analysis'!G65 -> 192259.07 | F24: ='[1]Variance Analysis'!J65 -> 42.600261
A25: ='[1]Variance Analysis'!A51 -> Location 2 | B25: ='[1]Variance Analysis'!B51 -> Position X | C25: ='[1]Variance Analysis'!C51 -> 743584.25 | D25: ='[1]Variance Analysis'!E51 -> 647008.2 | E25: ='[1]Variance Analysis'!G51 -> 96576.055 | F25: ='[1]Variance Analysis'!J51 -> 18.8
A26: ='[1]Variance Analysis'!A62 -> Location 3 | B26: ='[1]Variance Analysis'!B62 -> Position I | C26: ='[1]Variance Analysis'!C62 -> 634823.01 | D26: ='[1]Variance Analysis'!E62 -> 589056.97 | E26: ='[1]Variance Analysis'!G62 -> 45766.035 | F26: ='[1]Variance Analysis'!J62 -> -11.78
A27: ='[1]Variance Analysis'!A99 -> Location 4 | B27: ='[1]Variance Analysis'!B99 -> Position T | C27: ='[1]Variance Analysis'!C99 -> 2256338 | D27: ='[1]Variance Analysis'!E99 -> 2215244.2 | E27: ='[1]Variance Analysis'!G99 -> 41093.844 | F27: ='[1]Variance Analysis'!J99 -> 2.5703167
A28: ='[1]Variance Analysis'!A94 -> Location 4 | B28: ='[1]Variance Analysis'!B94 -> Position O | C28: ='[1]Variance Analysis'!C94 -> 314685.07 | D28: ='[1]Variance Analysis'!E94 -> 273965.4 | E28: ='[1]Variance Analysis'!G94 -> 40719.675 | F28: ='[1]Variance Analysis'!J94 -> 4.1944833
A29: ='[1]Variance Analysis'!A48 -> Location 2 | B29: ='[1]Variance Analysis'!B48 -> Position U | C29: ='[1]Variance Analysis'!C48 -> 202357.83 | D29: ='[1]Variance Analysis'!E48 -> 161886.26 | E29: ='[1]Variance Analysis'!G48 -> 40471.565 | F29: ='[1]Variance Analysis'!J48 -> 3.5

Sheet Variance Analysis
A1: Location | B1: Position | C1: Labor $ Cur.Fcst | D1: Labor $ Prior Fcst | E1: Labor $ Plan | F1: Labor $ Actual 2025 | G1: Var $ vs Plan (Budget) | H1: Var % vs Plan (Budget) | I1: Var $ vs Prior Fcst | J1: FTE Var vs Plan | K1: OT % of Salary (Cur.Fcst)
A2: ='Raw - Workforce'!A55 -> Location 3 | B2: ='Raw - Workforce'!B55 -> Position B | C2: ='Raw - Workforce'!G55+'Raw - Workforce'!K55 -> 1445020.5 | D2: ='Raw - Workforce'!H55+'Raw - Workforce'!L55 -> 1486914.3 | E2: ='Raw - Workforce'!I55+'Raw - Workforce'!M55 -> 1706992.9 | F2: ='Raw - Workforce'!J55+'Raw - Workforce'!N55 -> 1744438 | G2: =C2-E2 -> -261972.36 | H2: =IFERROR(G2/E2,0) -> -0.15347009 | I2: =C2-D2 -> -41893.785 | J2: ='Raw - Workforce'!C55-'Raw - Workforce'!E55 -> -82.074351 | K2: =IFERROR('Raw - Workforce'!K55/'Raw - Workforce'!G55,0) -> 0.17854426 | M2: currently ranked from min Var- Plan
A3: ='Raw - Workforce'!A61 -> Location 3 | B3: ='Raw - Workforce'!B61 -> Position H | C3: ='Raw - Workforce'!G61+'Raw - Workforce'!K61 -> 1252895 | D3: ='Raw - Workforce'!H61+'Raw - Workforce'!L61 -> 1274973.9 | E3: ='Raw - Workforce'!I61+'Raw - Workforce'!M61 -> 1457336.4 | F3: ='Raw - Workforce'!J61+'Raw - Workforce'!N61 -> 1449146 | G3: =C3-E3 -> -204441.42 | H3: =IFERROR(G3/E3,0) -> -0.1402843 | I3: =C3-D3 -> -22078.864 | J3: ='Raw - Workforce'!C61-'Raw - Workforce'!E61 -> -43.626628 | K3: =IFERROR('Raw - Workforce'!K61/'Raw - Workforce'!G61,0) -> 0.099223176
A4: ='Raw - Workforce'!A29 -> Location 2 | B4: ='Raw - Workforce'!B29 -> Position B | C4: ='Raw - Workforce'!G29+'Raw - Workforce'!K29 -> 1314928.6 | D4: ='Raw - Workforce'!H29+'Raw - Workforce'!L29 -> 1267658.3 | E4: ='Raw - Workforce'!I29+'Raw - Workforce'!M29 -> 1507894.1 | F4: ='Raw - Workforce'!J29+'Raw - Workforce'!N29 -> 1286692.2 | G4: =C4-E4 -> -192965.41 | H4: =IFERROR(G4/E4,0) -> -0.12797014 | I4: =C4-D4 -> 47270.339 | J4: ='Raw - Workforce'!C29-'Raw - Workforce'!E29 -> -65.99 | K4: =IFERROR('Raw - Workforce'!K29/'Raw - Workforce'!G29,0) -> 0.071724466 | M4: then reversed from greatest to least to observe favorable and unfavorable outcomes
A5: ='Raw - Workforce'!A80 -> Location 4 | B5: ='Raw - Workforce'!B80 -> Position A | C5: ='Raw - Workforce'!G80+'Raw - Workforce'!K80 -> 1560596.1 | D5: ='Raw - Workforce'!H80+'Raw - Workforce'!L80 -> 1688562.3 | E5: ='Raw - Workforce'!I80+'Raw - Workforce'!M80 -> 1735596.1 | F5: ='Raw - Workforce'!J80+'Raw - Workforce'!N80 -> 1651815.2 | G5: =C5-E5 -> -175000 | H5: =IFERROR(G5/E5,0) -> -0.10082991 | I5: =C5-D5 -> -127966.24 | J5: ='Raw - Workforce'!C80-'Raw - Workforce'!E80 -> -60 | K5: =IFERROR('Raw - Workforce'!K80/'Raw - Workforce'!G80,0) -> 0.11844628
A6: ='Raw - Workforce'!A54 -> Location 3 | B6: ='Raw - Workforce'!B54 -> Position A | C6: ='Raw - Workforce'!G54+'Raw - Workforce'!K54 -> 889662.46 | D6: ='Raw - Workforce'!H54+'Raw - Workforce'!L54 -> 855580.97 | E6: ='Raw - Workforce'!I54+'Raw - Workforce'!M54 -> 1055190.3 | F6: ='Raw - Workforce'!J54+'Raw - Workforce'!N54 -> 1017975.4 | G6: =C6-E6 -> -165527.81 | H6: =IFERROR(G6/E6,0) -> -0.15687011 | I6: =C6-D6 -> 34081.488 | J6: ='Raw - Workforce'!C54-'Raw - Workforce'!E54 -> -53.576846 | K6: =IFERROR('Raw - Workforce'!K54/'Raw - Workforce'!G54,0) -> 0.099182289
A7: ='Raw - Workforce'!A81 -> Location 4 | B7: ='Raw - Workforce'!B81 -> Position B | C7: ='Raw - Workforce'!G81+'Raw - Workforce'!K81 -> 2467569.9 | D7: ='Raw - Workforce'!H81+'Raw - Workforce'!L81 -> 2359061.8 | E7: ='Raw - Workforce'!I81+'Raw - Workforce'!M81 -> 2613599.1 | F7: ='Raw - Workforce'!J81+'Raw - Workforce'!N81 -> 2482689.4 | G7: =C7-E7 -> -146029.16 | H7: =IFERROR(G7/E7,0) -> -0.055872823 | I7: =C7-D7 -> 108508.16 | J7: ='Raw - Workforce'!C81-'Raw - Workforce'!E81 -> -62.9 | K7: =IFERROR('Raw - Workforce'!K81/'Raw - Workforce'!G81,0) -> 0.14475791
A8: ='Raw - Workforce'!A6 -> Location 1 | B8: ='Raw - Workforce'!B6 -> Position E | C8: ='Raw - Workforce'!G6+'Raw - Workforce'!K6 -> 116986.9 | D8: ='Raw - Workforce'!H6+'Raw - Workforce'!L6 -> 185360.55 | E8: ='Raw - Workforce'!I6+'Raw - Workforce'!M6 -> 248284.51 | F8: ='Raw - Workforce'!J6+'Raw - Workforce'!N6 -> 215242.21 | G8: =C8-E8 -> -131297.61 | H8: =IFERROR(G8/E8,0) -> -0.52881916 | I8: =C8-D8 -> -68373.641 | J8: ='Raw - Workforce'!C6-'Raw - Workforce'!E6 -> -24.456722 | K8: =IFERROR('Raw - Workforce'!K6/'Raw - Workforce'!G6,0) -> 0.24345613
A9: ='Raw - Workforce'!A22 -> Location 1 | B9: ='Raw - Workforce'!B22 -> Position U | C9: ='Raw - Workforce'!G22+'Raw - Workforce'!K22 -> 188589.42 | D9: ='Raw - Workforce'!H22+'Raw - Workforce'!L22 -> 188589.42 | E9: ='Raw - Workforce'!I22+'Raw - Workforce'!M22 -> 301888.72 | F9: ='Raw - Workforce'!J22+'Raw - Workforce'!N22 -> 287026.73 | G9: =C9-E9 -> -113299.29 | H9: =IFERROR(G9/E9,0) -> -0.37530151 | I9: =C9-D9 -> 0 | J9: ='Raw - Workforce'!C22-'Raw - Workforce'!E22 -> 1 | K9: =IFERROR('Raw - Workforce'!K22/'Raw - Workforce'!G22,0) -> -0.0016195801
A10: ='Raw - Workforce'!A13 -> Location 1 | B10: ='Raw - Workforce'!B13 -> Position L | C10: ='Raw - Workforce'!G13+'Raw - Workforce'!K13 -> 660012.41 | D10: ='Raw - Workforce'!H13+'Raw - Workforce'!L13 -> 660012.41 | E10: ='Raw - Workforce'!I13+'Raw - Workforce'!M13 -> 756530.2 | F10: ='Raw - Workforce'!J13+'Raw - Workforce'!N13 -> 690487.45 | G10: =C10-E10 -> -96517.79 | H10: =IFERROR(G10/E10,0) -> -0.12757956 | I10: =C10-D10 -> 0 | J10: ='Raw - Workforce'!C13-'Raw - Workforce'!E13 -> -32.418709 | K10: =IFERROR('Raw - Workforce'!K13/'Raw - Workforce'!G13,0) -> 0.15112895
A11: ='Raw - Workforce'!A12 -> Location 1 | B11: ='Raw - Workforce'!B12 -> Position K | C11: ='Raw - Workforce'!G12+'Raw - Workforce'!K12 -> 654204.24 | D11: ='Raw - Workforce'!H12+'Raw - Workforce'!L12 -> 654204.24 | E11: ='Raw - Workforce'!I12+'Raw - Workforce'!M12 -> 747824.4 | F11: ='Raw - Workforce'!J12+'Raw - Workforce'!N12 -> 658390.69 | G11: =C11-E11 -> -93620.153 | H11: =IFERROR(G11/E11,0) -> -0.12519002 | I11: =C11-D11 -> 0 | J11: ='Raw - Workforce'!C12-'Raw - Workforce'!E12 -> -16.59 | K11: =IFERROR('Raw - Workforce'!K12/'Raw - Workforce'!G12,0) -> 0.15112895
A12: ='Raw - Workforce'!A69 -> Location 3 | B12: ='Raw - Workforce'!B69 -> Position P | C12: ='Raw - Workforce'!G69+'Raw - Workforce'!K69 -> 515660.66 | D12: ='Raw - Workforce'!H69+'Raw - Workforce'!L69 -> 522817.51 | E12: ='Raw - Workforce'!I69+'Raw - Workforce'!M69 -> 600654.21 | F12: ='Raw - Workforce'!J69+'Raw - Workforce'!N69 -> 508169.82 | G12: =C12-E12 -> -84993.544 | H12: =IFERROR(G12/E12,0) -> -0.14150162 | I12: =C12-D12 -> -7156.8476 | J12: ='Raw - Workforce'!C69-'Raw - Workforce'!E69 -> -7.5 | K12: =IFERROR('Raw - Workforce'!K69/'Raw - Workforce'!G69,0) -> 0.10206544
A13: ='Raw - Workforce'!A77 -> Location 3 | B13: ='Raw - Workforce'!B77 -> Position X | C13: ='Raw - Workforce'!G77+'Raw - Workforce'!K77 -> 765628.09 | D13: ='Raw - Workforce'!H77+'Raw - Workforce'!L77 -> 760506.83 | E13: ='Raw - Workforce'!I77+'Raw - Workforce'!M77 -> 826019.44 | F13: ='Raw - Workforce'!J77+'Raw - Workforce'!N77 -> 777317.01 | G13: =C13-E13 -> -60391.352 | H13: =IFERROR(G13/E13,0) -> -0.073111296 | I13: =C13-D13 -> 5121.2581 | J13: ='Raw - Workforce'!C77-'Raw - Workforce'!E77 -> -13.88 | K13: =IFERROR('Raw - Workforce'!K77/'Raw - Workforce'!G77,0) -> 0
A14: ='Raw - Workforce'!A28 -> Location 2 | B14: ='Raw - Workforce'!B28 -> Position A | C14: ='Raw - Workforce'!G28+'Raw - Workforce'!K28 -> 1090197 | D14: ='Raw - Workforce'!H28+'Raw - Workforce'!L28 -> 1032113 | E14: ='Raw - Workforce'!I28+'Raw - Workforce'!M28 -> 1149261.3 | F14: ='Raw - Workforce'!J28+'Raw - Workforce'!N28 -> 1056739.5 | G14: =C14-E14 -> -59064.326 | H14: =IFERROR(G14/E14,0) -> -0.051393295 | I14: =C14-D14 -> 58083.98 | J14: ='Raw - Workforce'!C28-'Raw - Workforce'!E28 -> -25.56 | K14: =IFERROR('Raw - Workforce'!K28/'Raw - Workforce'!G28,0) -> 0.10278399
A15: ='Raw - Workforce'!A38 -> Location 2 | B15: ='Raw - Workforce'!B38 -> Position K | C15: ='Raw - Workforce'!G38+'Raw - Workforce'!K38 -> 443064.7 | D15: ='Raw - Workforce'!H38+'Raw - Workforce'!L38 -> 443064.7 | E15: ='Raw - Workforce'!I38+'Raw - Workforce'!M38 -> 493294.42 | F15: ='Raw - Workforce'!J38+'Raw - Workforce'!N38 -> 488091.83 | G15: =C15-E15 -> -50229.72 | H15: =IFERROR(G15/E15,0) -> -0.10182503 | I15: =C15-D15 -> 0 | J15: ='Raw - Workforce'!C38-'Raw - Workforce'!E38 -> -31.46 | K15: =IFERROR('Raw - Workforce'!K38/'Raw - Workforce'!G38,0) -> 0.047969925
A16: ='Raw - Workforce'!A95 -> Location 4 | B16: ='Raw - Workforce'!B95 -> Position P | C16: ='Raw - Workforce'!G95+'Raw - Workforce'!K95 -> 720860.12 | D16: ='Raw - Workforce'!H95+'Raw - Workforce'!L95 -> 730860.12 | E16: ='Raw - Workforce'!I95+'Raw - Workforce'!M95 -> 765042.52 | F16: ='Raw - Workforce'!J95+'Raw - Workforce'!N95 -> 776666.77 | G16: =C16-E16 -> -44182.402 | H16: =IFERROR(G16/E16,0) -> -0.057751564 | I16: =C16-D16 -> -10000 | J16: ='Raw - Workforce'!C95-'Raw - Workforce'!E95 -> -8.2583333 | K16: =IFERROR('Raw - Workforce'!K95/'Raw - Workforce'!G95,0) -> 0.079624755
A17: ='Raw - Workforce'!A39 -> Location 2 | B17: ='Raw - Workforce'!B39 -> Position L | C17: ='Raw - Workforce'!G39+'Raw - Workforce'!K39 -> 336023.19 | D17: ='Raw - Workforce'!H39+'Raw - Workforce'!L39 -> 337174.23 | E17: ='Raw - Workforce'!I39+'Raw - Workforce'!M39 -> 380200.14 | F17: ='Raw - Workforce'!J39+'Raw - Workforce'!N39 -> 332506.43 | G17: =C17-E17 -> -44176.946 | H17: =IFERROR(G17/E17,0) -> -0.11619392 | I17: =C17-D17 -> -1151.0408 | J17: ='Raw - Workforce'!C39-'Raw - Workforce'!E39 -> -19.19 | K17: =IFERROR('Raw - Workforce'!K39/'Raw - Workforce'!G39,0) -> 0.056109794
A18: ='Raw - Workforce'!A31 -> Location 2 | B18: ='Raw - Workforce'!B31 -> Position D | C18: ='Raw - Workforce'!G31+'Raw - Workforce'!K31 -> 84744.859 | D18: ='Raw - Workforce'!H31+'Raw - Workforce'!L31 -> 79136.859 | E18: ='Raw - Workforce'!I31+'Raw - Workforce'!M31 -> 121165.07 | F18: ='Raw - Workforce'!J31+'Raw - Workforce'!N31 -> 118985.56 | G18: =C18-E18 -> -36420.212 | H18: =IFERROR(G18/E18,0) -> -0.30058343 | I18: =C18-D18 -> 5608 | J18: ='Raw - Workforce'!C31-'Raw - Workforce'!E31 -> -16.27 | K18: =IFERROR('Raw - Workforce'!K31/'Raw - Workforce'!G31,0) -> 0.099012566
A19: ='Raw - Workforce'!A100 -> Location 4 | B19: ='Raw - Workforce'!B100 -> Position U | C19: ='Raw - Workforce'!G100+'Raw - Workforce'!K100 -> 337062.55 | D19: ='Raw - Workforce'!H100+'Raw - Workforce'!L100 -> 337760.55 | E19: ='Raw - Workforce'!I100+'Raw - Workforce'!M100 -> 369062.55 | F19: ='Raw - Workforce'!J100+'Raw - Workforce'!N100 -> 361260.55 | G19: =C19-E19 -> -32000 | H19: =IFERROR(G19/E19,0) -> -0.086706169 | I19: =C19-D19 -> -698 | J19: ='Raw - Workforce'!C100-'Raw - Workforce'!E100 -> 0.6 | K19: =IFERROR('Raw - Workforce'!K100/'Raw - Workforce'!G100,0) -> 0
A20: ='Raw - Workforce'!A24 -> Location 1 | B20: ='Raw - Workforce'!B24 -> Position W | C20: ='Raw - Workforce'!G24+'Raw - Workforce'!K24 -> -3.6379788e-12 | D20: ='Raw - Workforce'!H24+'Raw - Workforce'!L24 -> -3.6379788e-12 | E20: ='Raw - Workforce'!I24+'Raw - Workforce'!M24 -> 31615.827 | F20: ='Raw - Workforce'!J24+'Raw - Workforce'!N24 -> 88800.08 | G20: =C20-E20 -> -31615.827 | H20: =IFERROR(G20/E20,0) -> -1 | I20: =C20-D20 -> 0 | J20: ='Raw - Workforce'!C24-'Raw - Workforce'!E24 -> -0.5 | K20: =IFERROR('Raw - Workforce'!K24/'Raw - Workforce'!G24,0) -> 0
A21: ='Raw - Workforce'!A73 -> Location 3 | B21: ='Raw - Workforce'!B73 -> Position T | C21: ='Raw - Workforce'!G73+'Raw - Workforce'!K73 -> 1681988.2 | D21: ='Raw - Workforce'!H73+'Raw - Workforce'!L73 -> 1717285.7 | E21: ='Raw - Workforce'!I73+'Raw - Workforce'!M73 -> 1712862.5 | F21: ='Raw - Workforce'!J73+'Raw - Workforce'!N73 -> 1646223 | G21: =C21-E21 -> -30874.383 | H21: =IFERROR(G21/E21,0) -> -0.018025021 | I21: =C21-D21 -> -35297.55 | J21: ='Raw - Workforce'!C73-'Raw - Workforce'!E73 -> 4.4330119 | K21: =IFERROR('Raw - Workforce'!K73/'Raw - Workforce'!G73,0) -> 0.080812796
A22: ='Raw - Workforce'!A16 -> Location 1 | B22: ='Raw - Workforce'!B16 -> Position O | C22: ='Raw - Workforce'!G16+'Raw - Workforce'!K16 -> 157550.22 | D22: ='Raw - Workforce'!H16+'Raw - Workforce'!L16 -> 157550.22 | E22: ='Raw - Workforce'!I16+'Raw - Workforce'!M16 -> 187654.9 | F22: ='Raw - Workforce'!J16+'Raw - Workforce'!N16 -> 179832.32 | G22: =C22-E22 -> -30104.681 | H22: =IFERROR(G22/E22,0) -> -0.16042576 | I22: =C22-D22 -> 0 | J22: ='Raw - Workforce'!C16-'Raw - Workforce'!E16 -> -10.713423 | K22: =IFERROR('Raw - Workforce'!K16/'Raw - Workforce'!G16,0) -> 0.22645103
A23: ='Raw - Workforce'!A57 -> Location 3 | B23: ='Raw - Workforce'!B57 -> Position D | C23: ='Raw - Workforce'!G57+'Raw - Workforce'!K57 -> 0 | D23: ='Raw - Workforce'!H57+'Raw - Workforce'!L57 -> 0 | E23: ='Raw - Workforce'!I57+'Raw - Workforce'!M57 -> 30047.743 | F23: ='Raw - Workforce'!J57+'Raw - Workforce'!N57 -> 10975.15 | G23: =C23-E23 -> -30047.743 | H23: =IFERROR(G23/E23,0) -> -1 | I23: =C23-D23 -> 0 | J23: ='Raw - Workforce'!C57-'Raw - Workforce'!E57 -> -8.5 | K23: =IFERROR('Raw - Workforce'!K57/'Raw - Workforce'!G57,0) -> 0
A24: ='Raw - Workforce'!A52 -> Location 2 | B24: ='Raw - Workforce'!B52 -> Position Y | C24: ='Raw - Workforce'!G52+'Raw - Workforce'!K52 -> 154633.49 | D24: ='Raw - Workforce'!H52+'Raw - Workforce'!L52 -> 154633.49 | E24: ='Raw - Workforce'!I52+'Raw - Workforce'!M52 -> 183627.27 | F24: ='Raw - Workforce'!J52+'Raw - Workforce'!N52 -> 0 | G24: =C24-E24 -> -28993.78 | H24: =IFERROR(G24/E24,0) -> -0.15789474 | I24: =C24-D24 -> 0 | J24: ='Raw - Workforce'!C52-'Raw - Workforce'!E52 -> -3 | K24: =IFERROR('Raw - Workforce'!K52/'Raw - Workforce'!G52,0) -> 0
A25: ='Raw - Workforce'!A3 -> Location 1 | B25: ='Raw - Workforce'!B3 -> Position B | C25: ='Raw - Workforce'!G3+'Raw - Workforce'!K3 -> 1650151 | D25: ='Raw - Workforce'!H3+'Raw - Workforce'!L3 -> 1673096.8 | E25: ='Raw - Workforce'!I3+'Raw - Workforce'!M3 -> 1678200.4 | F25: ='Raw - Workforce'!J3+'Raw - Workforce'!N3 -> 1469307.8 | G25: =C25-E25 -> -28049.437 | H25: =IFERROR(G25/E25,0) -> -0.016713997 | I25: =C25-D25 -> -22945.85 | J25: ='Raw - Workforce'!C3-'Raw - Workforce'!E3 -> -44.673278 | K25: =IFERROR('Raw - Workforce'!K3/'Raw - Workforce'!G3,0) -> 0.21106855
A26: ='Raw - Workforce'!A33 -> Location 2 | B26: ='Raw - Workforce'!B33 -> Position F | C26: ='Raw - Workforce'!G33+'Raw - Workforce'!K33 -> 44224.196 | D26: ='Raw - Workforce'!H33+'Raw - Workforce'!L33 -> 44224.196 | E26: ='Raw - Workforce'!I33+'Raw - Workforce'!M33 -> 70518.748 | F26: ='Raw - Workforce'!J33+'Raw - Workforce'!N33 -> 66201.63 | G26: =C26-E26 -> -26294.553 | H26: =IFERROR(G26/E26,0) -> -0.37287322 | I26: =C26-D26 -> 0 | J26: ='Raw - Workforce'!C33-'Raw - Workforce'!E33 -> -10.86 | K26: =IFERROR('Raw - Workforce'!K33/'Raw - Workforce'!G33,0) -> 0.11034535
A27: ='Raw - Workforce'!A23 -> Location 1 | B27: ='Raw - Workforce'!B23 -> Position V | C27: ='Raw - Workforce'!G23+'Raw - Workforce'!K23 -> 160650.25 | D27: ='Raw - Workforce'!H23+'Raw - Workforce'!L23 -> 160650.25 | E27: ='Raw - Workforce'!I23+'Raw - Workforce'!M23 -> 186792.57 | F27: ='Raw - Workforce'!J23+'Raw - Workforce'!N23 -> 149000.3 | G27: =C27-E27 -> -26142.315 | H27: =IFERROR(G27/E27,0) -> -0.13995372 | I27: =C27-D27 -> 0 | J27: ='Raw - Workforce'!C23-'Raw - Workforce'!E23 -> 0 | K27: =IFERROR('Raw - Workforce'!K23/'Raw - Workforce'!G23,0) -> -0.0016195801
A28: ='Raw - Workforce'!A2 -> Location 1 | B28: ='Raw - Workforce'!B2 -> Position A | C28: ='Raw - Workforce'!G2+'Raw - Workforce'!K2 -> 1314625.2 | D28: ='Raw - Workforce'!H2+'Raw - Workforce'!L2 -> 1318388.6 | E28: ='Raw - Workforce'!I2+'Raw - Workforce'!M2 -> 1339965.4 | F28: ='Raw - Workforce'!J2+'Raw - Workforce'!N2 -> 1283926.9 | G28: =C28-E28 -> -25340.162 | H28: =IFERROR(G28/E28,0) -> -0.018911057 | I28: =C28-D28 -> -3763.4062 | J28: ='Raw - Workforce'!C2-'Raw - Workforce'!E2 -> -17.286202 | K28: =IFERROR('Raw - Workforce'!K2/'Raw - Workforce'!G2,0) -> 0.18321702
A29: ='Raw - Workforce'!A88 -> Location 4 | B29: ='Raw - Workforce'!B88 -> Position I | C29: ='Raw - Workforce'!G88+'Raw - Workforce'!K88 -> 351680.68 | D29: ='Raw - Workforce'!H88+'Raw - Workforce'!L88 -> 356280.68 | E29: ='Raw - Workforce'!I88+'Raw - Workforce'!M88 -> 375851.68 | F29: ='Raw - Workforce'!J88+'Raw - Workforce'!N88 -> 359971.02 | G29: =C29-E29 -> -24171 | H29: =IFERROR(G29/E29,0) -> -0.064309943 | I29: =C29-D29 -> -4600 | J29: ='Raw - Workforce'!C88-'Raw - Workforce'!E88 -> -9.5 | K29: =IFERROR('Raw - Workforce'!K88/'Raw - Workforce'!G88,0) -> 0.097540753
A30: ='Raw - Workforce'!A50 -> Location 2 | B30: ='Raw - Workforce'!B50 -> Position W | C30: ='Raw - Workforce'!G50+'Raw - Workforce'!K50 -> 13841.685 | D30: ='Raw - Workforce'!H50+'Raw - Workforce'!L50 -> 941.68467 | E30: ='Raw - Workforce'!I50+'Raw - Workforce'!M50 -> 35400.47 | F30: ='Raw - Workforce'!J50+'Raw - Workforce'!N50 -> 48138.02 | G30: =C30-E30 -> -21558.785 | H30: =IFERROR(G30/E30,0) -> -0.60899715 | I30: =C30-D30 -> 12900 | J30: ='Raw - Workforce'!C50-'Raw - Workforce'!E50 -> -6.34 | K30: =IFERROR('Raw - Workforce'!K50/'Raw - Workforce'!G50,0) -> 0.072998812
A31: ='Raw - Workforce'!A7 -> Location 1 | B31: ='Raw - Workforce'!B7 -> Position F | C31: ='Raw - Workforce'!G7+'Raw - Workforce'!K7 -> 87904.33 | D31: ='Raw - Workforce'!H7+'Raw - Workforce'!L7 -> 90845.556 | E31: ='Raw - Workforce'!I7+'Raw - Workforce'!M7 -> 107694.18 | F31: ='Raw - Workforce'!J7+'Raw - Workforce'!N7 -> 55439.6 | G31: =C31-E31 -> -19789.85 | H31: =IFERROR(G31/E31,0) -> -0.1837597 | I31: =C31-D31 -> -2941.2262 | J31: ='Raw - Workforce'!C7-'Raw - Workforce'!E7 -> -3.9 | K31: =IFERROR('Raw - Workforce'!K7/'Raw - Workforce'!G7,0) -> 0.1463995
A32: ='Raw - Workforce'!A43 -> Location 2 | B32: ='Raw - Workforce'!B43 -> Position P | C32: ='Raw - Workforce'!G43+'Raw - Workforce'!K43 -> 407779.44 | D32: ='Raw - Workforce'!H43+'Raw - Workforce'!L43 -> 411869.41 | E32: ='Raw - Workforce'!I43+'Raw - Workforce'!M43 -> 424795.8 | F32: ='Raw - Workforce'!J43+'Raw - Workforce'!N43 -> 430909.74 | G32: =C32-E32 -> -17016.357 | H32: =IFERROR(G32/E32,0) -> -0.040057733 | I32: =C32-D32 -> -4089.971 | J32: ='Raw - Workforce'!C43-'Raw - Workforce'!E43 -> -8.0315064 | K32: =IFERROR('Raw - Workforce'!K43/'Raw - Workforce'!G43,0) -> 0.12912834
A33: ='Raw - Workforce'!A87 -> Location 4 | B33: ='Raw - Workforce'!B87 -> Position H | C33: ='Raw - Workforce'!G87+'Raw - Workforce'!K87 -> 1119106.8 | D33: ='Raw - Workforce'!H87+'Raw - Workforce'!L87 -> 1139106.8 | E33: ='Raw - Workforce'!I87+'Raw - Workforce'!M87 -> 1136024.8 | F33: ='Raw - Workforce'!J87+'Raw - Workforce'!N87 -> 987809.41 | G33: =C33-E33 -> -16918 | H33: =IFERROR(G33/E33,0) -> -0.014892281 | I33: =C33-D33 -> -20000 | J33: ='Raw - Workforce'!C87-'Raw - Workforce'!E87 -> -11.6 | K33: =IFERROR('Raw - Workforce'!K87/'Raw - Workforce'!G87,0) -> 0.070535698
A34: ='Raw - Workforce'!A97 -> Location 4 | B34: ='Raw - Workforce'!B97 -> Position R | C34: ='Raw - Workforce'!G97+'Raw - Workforce'!K97 -> 262229.54 | D34: ='Raw - Workforce'!H97+'Raw - Workforce'!L97 -> 269229.54 | E34: ='Raw - Workforce'!I97+'Raw - Workforce'!M97 -> 273446.69 | F34: ='Raw - Workforce'!J97+'Raw - Workforce'!N97 -> 182320.05 | G34: =C34-E34 -> -11217.145 | H34: =IFERROR(G34/E34,0) -> -0.041021325 | I34: =C34-D34 -> -7000 | J34: ='Raw - Workforce'!C97-'Raw - Workforce'!E97 -> -4.01 | K34: =IFERROR('Raw - Workforce'!K97/'Raw - Workforce'!G97,0) -> 0.048245222
A35: ='Raw - Workforce'!A103 -> Location 4 | B35: ='Raw - Workforce'!B103 -> Position X | C35: ='Raw - Workforce'!G103+'Raw - Workforce'!K103 -> 1136975.6 | D35: ='Raw - Workforce'!H103+'Raw - Workforce'!L103 -> 1136975.6 | E35: ='Raw - Workforce'!I103+'Raw - Workforce'!M103 -> 1147522.6 | F35: ='Raw - Workforce'!J103+'Raw - Workforce'!N103 -> 936301.12 | G35: =C35-E35 -> -10547 | H35: =IFERROR(G35/E35,0) -> -0.009191104 | I35: =C35-D35 -> 0 | J35: ='Raw - Workforce'!C103-'Raw - Workforce'!E103 -> -2.1 | K35: =IFERROR('Raw - Workforce'!K103/'Raw - Workforce'!G103,0) -> 0
A36: ='Raw - Workforce'!A10 -> Location 1 | B36: ='Raw - Workforce'!B10 -> Position I | C36: ='Raw - Workforce'!G10+'Raw - Workforce'!K10 -> 334192.45 | D36: ='Raw - Workforce'!H10+'Raw - Workforce'!L10 -> 334192.45 | E36: ='Raw - Workforce'!I10+'Raw - Workforce'!M10 -> 343557.18 | F36: ='Raw - Workforce'!J10+'Raw - Workforce'!N10 -> 333783.6 | G36: =C36-E36 -> -9364.7229 | H36: =IFERROR(G36/E36,0) -> -0.02725812 | I36: =C36-D36 -> 0 | J36: ='Raw - Workforce'!C10-'Raw - Workforce'!E10 -> 2.25 | K36: =IFERROR('Raw - Workforce'!K10/'Raw - Workforce'!G10,0) -> 0.15324713
A37: ='Raw - Workforce'!A21 -> Location 1 | B37: ='Raw - Workforce'!B21 -> Position T | C37: ='Raw - Workforce'!G21+'Raw - Workforce'!K21 -> 1201881.1 | D37: ='Raw - Workforce'!H21+'Raw - Workforce'!L21 -> 1201881.1 | E37: ='Raw - Workforce'!I21+'Raw - Workforce'!M21 -> 1210884.5 | F37: ='Raw - Workforce'!J21+'Raw - Workforce'!N21 -> 1213868.9 | G37: =C37-E37 -> -9003.4138 | H37: =IFERROR(G37/E37,0) -> -0.0074354029 | I37: =C37-D37 -> 0 | J37: ='Raw - Workforce'!C21-'Raw - Workforce'!E21 -> -9.8067154 | K37: =IFERROR('Raw - Workforce'!K21/'Raw - Workforce'!G21,0) -> 0.10111883
A38: ='Raw - Workforce'!A101 -> Location 4 | B38: ='Raw - Workforce'!B101 -> Position V | C38: ='Raw - Workforce'!G101+'Raw - Workforce'!K101 -> 196135.16 | D38: ='Raw - Workforce'!H101+'Raw - Workforce'!L101 -> 196135.16 | E38: ='Raw - Workforce'!I101+'Raw - Workforce'!M101 -> 203622.16 | F38: ='Raw - Workforce'!J101+'Raw - Workforce'!N101 -> 199587.02 | G38: =C38-E38 -> -7487 | H38: =IFERROR(G38/E38,0) -> -0.036769083 | I38: =C38-D38 -> 0 | J38: ='Raw - Workforce'!C101-'Raw - Workforce'!E101 -> 0 | K38: =IFERROR('Raw - Workforce'!K101/'Raw - Workforce'!G101,0) -> 0
A39: ='Raw - Workforce'!A85 -> Location 4 | B39: ='Raw - Workforce'!B85 -> Position F | C39: ='Raw - Workforce'!G85+'Raw - Workforce'!K85 -> 196337.37 | D39: ='Raw - Workforce'!H85+'Raw - Workforce'!L85 -> 188708.32 | E39: ='Raw - Workforce'!I85+'Raw - Workforce'!M85 -> 203337.37 | F39: ='Raw - Workforce'!J85+'Raw - Workforce'!N85 -> 244749.3 | G39: =C39-E39 -> -7000 | H39: =IFERROR(G39/E39,0) -> -0.034425546 | I39: =C39-D39 -> 7629.0557 | J39: ='Raw - Workforce'!C85-'Raw - Workforce'!E85 -> -1.7 | K39: =IFERROR('Raw - Workforce'!K85/'Raw - Workforce'!G85,0) -> 0.1175757
A40: ='Raw - Workforce'!A84 -> Location 4 | B40: ='Raw - Workforce'!B84 -> Position E | C40: ='Raw - Workforce'!G84+'Raw - Workforce'!K84 -> 330340.16 | D40: ='Raw - Workforce'!H84+'Raw - Workforce'!L84 -> 330340.16 | E40: ='Raw - Workforce'!I84+'Raw - Workforce'!M84 -> 336857.16 | F40: ='Raw - Workforce'!J84+'Raw - Workforce'!N84 -> 371830.14 | G40: =C40-E40 -> -6517 | H40: =IFERROR(G40/E40,0) -> -0.019346479 | I40: =C40-D40 -> 0 | J40: ='Raw - Workforce'!C84-'Raw - Workforce'!E84 -> -4.6 | K40: =IFERROR('Raw - Workforce'!K84/'Raw - Workforce'!G84,0) -> 0.066262065
A41: ='Raw - Workforce'!A19 -> Location 1 | B41: ='Raw - Workforce'!B19 -> Position R | C41: ='Raw - Workforce'!G19+'Raw - Workforce'!K19 -> 70022.017 | D41: ='Raw - Workforce'!H19+'Raw - Workforce'!L19 -> 70022.017 | E41: ='Raw - Workforce'!I19+'Raw - Workforce'!M19 -> 76384.725 | F41: ='Raw - Workforce'!J19+'Raw - Workforce'!N19 -> 44669.03 | G41: =C41-E41 -> -6362.708 | H41: =IFERROR(G41/E41,0) -> -0.083298172 | I41: =C41-D41 -> 0 | J41: ='Raw - Workforce'!C19-'Raw - Workforce'!E19 -> -2.8174198 | K41: =IFERROR('Raw - Workforce'!K19/'Raw - Workforce'!G19,0) -> 0.12076404
A42: ='Raw - Workforce'!A72 -> Location 3 | B42: ='Raw - Workforce'!B72 -> Position S | C42: ='Raw - Workforce'!G72+'Raw - Workforce'!K72 -> 315765.45 | D42: ='Raw - Workforce'!H72+'Raw - Workforce'!L72 -> 322483.86 | E42: ='Raw - Workforce'!I72+'Raw - Workforce'!M72 -> 322098.57 | F42: ='Raw - Workforce'!J72+'Raw - Workforce'!N72 -> 295101.42 | G42: =C42-E42 -> -6333.1276 | H42: =IFERROR(G42/E42,0) -> -0.019662079 | I42: =C42-D42 -> -6718.4137 | J42: ='Raw - Workforce'!C72-'Raw - Workforce'!E72 -> -1.26 | K42: =IFERROR('Raw - Workforce'!K72/'Raw - Workforce'!G72,0) -> 0
A43: ='Raw - Workforce'!A83 -> Location 4 | B43: ='Raw - Workforce'!B83 -> Position D | C43: ='Raw - Workforce'!G83+'Raw - Workforce'!K83 -> 98436.091 | D43: ='Raw - Workforce'!H83+'Raw - Workforce'!L83 -> 106896.09 | E43: ='Raw - Workforce'!I83+'Raw - Workforce'!M83 -> 104436.09 | F43: ='Raw - Workforce'!J83+'Raw - Workforce'!N83 -> 134835.29 | G43: =C43-E43 -> -6000 | H43: =IFERROR(G43/E43,0) -> -0.057451404 | I43: =C43-D43 -> -8460 | J43: ='Raw - Workforce'!C83-'Raw - Workforce'!E83 -> -3.2 | K43: =IFERROR('Raw - Workforce'!K83/'Raw - Workforce'!G83,0) -> 0.090275234
A44: ='Raw - Workforce'!A5 -> Location 1 | B44: ='Raw - Workforce'!B5 -> Position D | C44: ='Raw - Workforce'!G5+'Raw - Workforce'!K5 -> 59078.241 | D44: ='Raw - Workforce'!H5+'Raw - Workforce'!L5 -> 59078.241 | E44: ='Raw - Workforce'!I5+'Raw - Workforce'!M5 -> 62985.981 | F44: ='Raw - Workforce'!J5+'Raw - Workforce'!N5 -> 66237.47 | G44: =C44-E44 -> -3907.7401 | H44: =IFERROR(G44/E44,0) -> -0.062041427 | I44: =C44-D44 -> 0 | J44: ='Raw - Workforce'!C5-'Raw - Workforce'!E5 -> -1.3607295 | K44: =IFERROR('Raw - Workforce'!K5/'Raw - Workforce'!G5,0) -> 0.14099138
A45: ='Raw - Workforce'!A49 -> Location 2 | B45: ='Raw - Workforce'!B49 -> Position V | C45: ='Raw - Workforce'!G49+'Raw - Workforce'!K49 -> 134453 | D45: ='Raw - Workforce'!H49+'Raw - Workforce'!L49 -> 134453 | E45: ='Raw - Workforce'!I49+'Raw - Workforce'!M49 -> 138329 | F45: ='Raw - Workforce'!J49+'Raw - Workforce'!N49 -> 130861.82 | G45: =C45-E45 -> -3876 | H45: =IFERROR(G45/E45,0) -> -0.028020155 | I45: =C45-D45 -> 0 | J45: ='Raw - Workforce'!C49-'Raw - Workforce'!E49 -> 0 | K45: =IFERROR('Raw - Workforce'!K49/'Raw - Workforce'!G49,0) -> 0
A46: ='Raw - Workforce'!A11 -> Location 1 | B46: ='Raw - Workforce'!B11 -> Position J | C46: ='Raw - Workforce'!G11+'Raw - Workforce'!K11 -> 0 | D46: ='Raw - Workforce'!H11+'Raw - Workforce'!L11 -> 0 | E46: ='Raw - Workforce'!I11+'Raw - Workforce'!M11 -> 3646.0644 | F46: ='Raw - Workforce'!J11+'Raw - Workforce'!N11 -> 3492.59 | G46: =C46-E46 -> -3646.0644 | H46: =IFERROR(G46/E46,0) -> -1 | I46: =C46-D46 -> 0 | J46: ='Raw - Workforce'!C11-'Raw - Workforce'!E11 -> -1 | K46: =IFERROR('Raw - Workforce'!K11/'Raw - Workforce'!G11,0) -> 0
A47: ='Raw - Workforce'!A40 -> Location 2 | B47: ='Raw - Workforce'!B40 -> Position M | C47: ='Raw - Workforce'!G40+'Raw - Workforce'!K40 -> 120729.64 | D47: ='Raw - Workforce'!H40+'Raw - Workforce'!L40 -> 124245.48 | E47: ='Raw - Workforce'!I40+'Raw - Workforce'!M40 -> 123545.48 | F47: ='Raw - Workforce'!J40+'Raw - Workforce'!N40 -> 114626.14 | G47: =C47-E47 -> -2815.8359 | H47: =IFERROR(G47/E47,0) -> -0.022791898 | I47: =C47-D47 -> -3515.837 | J47: ='Raw - Workforce'!C40-'Raw - Workforce'!E40 -> -0.84605932 | K47: =IFERROR('Raw - Workforce'!K40/'Raw - Workforce'!G40,0) -> 0.11496079
A48: ='Raw - Workforce'!A96 -> Location 4 | B48: ='Raw - Workforce'!B96 -> Position Q | C48: ='Raw - Workforce'!G96+'Raw - Workforce'!K96 -> 15020.198 | D48: ='Raw - Workforce'!H96+'Raw - Workforce'!L96 -> 15020.198 | E48: ='Raw - Workforce'!I96+'Raw - Workforce'!M96 -> 16050.215 | F48: ='Raw - Workforce'!J96+'Raw - Workforce'!N96 -> 11827.87 | G48: =C48-E48 -> -1030.0166 | H48: =IFERROR(G48/E48,0) -> -0.064174628 | I48: =C48-D48 -> 0 | J48: ='Raw - Workforce'!C96-'Raw - Workforce'!E96 -> 0.07 | K48: =IFERROR('Raw - Workforce'!K96/'Raw - Workforce'!G96,0) -> 0.090934193
A49: ='Raw - Workforce'!A44 -> Location 2 | B49: ='Raw - Workforce'!B44 -> Position Q | C49: ='Raw - Workforce'!G44+'Raw - Workforce'!K44 -> 6658.9049 | D49: ='Raw - Workforce'!H44+'Raw - Workforce'!L44 -> 5956.1642 | E49: ='Raw - Workforce'!I44+'Raw - Workforce'!M44 -> 7305.5907 | F49: ='Raw - Workforce'!J44+'Raw - Workforce'!N44 -> 7981.23 | G49: =C49-E49 -> -646.68579 | H49: =IFERROR(G49/E49,0) -> -0.088519302 | I49: =C49-D49 -> 702.74069 | J49: ='Raw - Workforce'!C44-'Raw - Workforce'!E44 -> -0.15 | K49: =IFERROR('Raw - Workforce'!K44/'Raw - Workforce'!G44,0) -> 0.029697111
A50: ='Raw - Workforce'!A70 -> Location 3 | B50: ='Raw - Workforce'!B70 -> Position Q | C50: ='Raw - Workforce'!G70+'Raw - Workforce'!K70 -> 40543.888 | D50: ='Raw - Workforce'!H70+'Raw - Workforce'!L70 -> 43922.546 | E50: ='Raw - Workforce'!I70+'Raw - Workforce'!M70 -> 40976.285 | F50: ='Raw - Workforce'!J70+'Raw - Workforce'!N70 -> 38810.49 | G50: =C50-E50 -> -432.39716 | H50: =IFERROR(G50/E50,0) -> -0.010552376 | I50: =C50-D50 -> -3378.6574 | J50: ='Raw - Workforce'!C70-'Raw - Workforce'!E70 -> -0.39666667 | K50: =IFERROR('Raw - Workforce'!K70/'Raw - Workforce'!G70,0) -> 0.097374408
A51: ='Raw - Workforce'!A8 -> Location 1 | B51: ='Raw - Workforce'!B8 -> Position G | C51: ='Raw - Workforce'!G8+'Raw - Workforce'!K8 -> 52524.517 | D51: ='Raw - Workforce'!H8+'Raw - Workforce'!L8 -> 52524.517 | E51: ='Raw - Workforce'!I8+'Raw - Workforce'!M8 -> 52929.408 | F51: ='Raw - Workforce'!J8+'Raw - Workforce'!N8 -> 54128.43 | G51: =C51-E51 -> -404.89093 | H51: =IFERROR(G51/E51,0) -> -0.0076496403 | I51: =C51-D51 -> 0 | J51: ='Raw - Workforce'!C8-'Raw - Workforce'!E8 -> -0.5013805 | K51: =IFERROR('Raw - Workforce'!K8/'Raw - Workforce'!G8,0) -> 0.14099138
A52: ='Raw - Workforce'!A4 -> Location 1 | B52: ='Raw - Workforce'!B4 -> Position C | C52: ='Raw - Workforce'!G4+'Raw - Workforce'!K4 -> 0 | D52: ='Raw - Workforce'!H4+'Raw - Workforce'!L4 -> 0 | E52: ='Raw - Workforce'!I4+'Raw - Workforce'!M4 -> 0 | F52: ='Raw - Workforce'!J4+'Raw - Workforce'!N4 -> 0 | G52: =C52-E52 -> 0 | H52: =IFERROR(G52/E52,0) -> 0 | I52: =C52-D52 -> 0 | J52: ='Raw - Workforce'!C4-'Raw - Workforce'!E4 -> 0 | K52: =IFERROR('Raw - Workforce'!K4/'Raw - Workforce'!G4,0) -> 0
A53: ='Raw - Workforce'!A20 -> Location 1 | B53: ='Raw - Workforce'!B20 -> Position S | C53: ='Raw - Workforce'!G20+'Raw - Workforce'!K20 -> 271804.09 | D53: ='Raw - Workforce'!H20+'Raw - Workforce'!L20 -> 271804.09 | E53: ='Raw - Workforce'!I20+'Raw - Workforce'!M20 -> 271804.09 | F53: ='Raw - Workforce'!J20+'Raw - Workforce'!N20 -> 261783.09 | G53: =C53-E53 -> 0 | H53: =IFERROR(G53/E53,0) -> 0 | I53: =C53-D53 -> 0 | J53: ='Raw - Workforce'!C20-'Raw - Workforce'!E20 -> -0.1 | K53: =IFERROR('Raw - Workforce'!K20/'Raw - Workforce'!G20,0) -> 0
A54: ='Raw - Workforce'!A26 -> Location 1 | B54: ='Raw - Workforce'!B26 -> Position Y | C54: ='Raw - Workforce'!G26+'Raw - Workforce'!K26 -> 0 | D54: ='Raw - Workforce'!H26+'Raw - Workforce'!L26 -> 0 | E54: ='Raw - Workforce'!I26+'Raw - Workforce'!M26 -> 0 | F54: ='Raw - Workforce'!J26+'Raw - Workforce'!N26 -> 0 | G54: =C54-E54 -> 0 | H54: =IFERROR(G54/E54,0) -> 0 | I54: =C54-D54 -> 0 | J54: ='Raw - Workforce'!C26-'Raw - Workforce'!E26 -> 0 | K54: =IFERROR('Raw - Workforce'!K26/'Raw - Workforce'!G26,0) -> 0
A55: ='Raw - Workforce'!A27 -> Location 1 | B55: ='Raw - Workforce'!B27 -> Position Z | C55: ='Raw - Workforce'!G27+'Raw - Workforce'!K27 -> 0 | D55: ='Raw - Workforce'!H27+'Raw - Workforce'!L27 -> 0 | E55: ='Raw - Workforce'!I27+'Raw - Workforce'!M27 -> 0 | F55: ='Raw - Workforce'!J27+'Raw - Workforce'!N27 -> 0 | G55: =C55-E55 -> 0 | H55: =IFERROR(G55/E55,0) -> 0 | I55: =C55-D55 -> 0 | J55: ='Raw - Workforce'!C27-'Raw - Workforce'!E27 -> 0 | K55: =IFERROR('Raw - Workforce'!K27/'Raw - Workforce'!G27,0) -> 0
A56: ='Raw - Workforce'!A30 -> Location 2 | B56: ='Raw - Workforce'!B30 -> Position C | C56: ='Raw - Workforce'!G30+'Raw - Workforce'!K30 -> 0 | D56: ='Raw - Workforce'!H30+'Raw - Workforce'!L30 -> 0 | E56: ='Raw - Workforce'!I30+'Raw - Workforce'!M30 -> 0 | F56: ='Raw - Workforce'!J30+'Raw - Workforce'!N30 -> 0 | G56: =C56-E56 -> 0 | H56: =IFERROR(G56/E56,0) -> 0 | I56: =C56-D56 -> 0 | J56: ='Raw - Workforce'!C30-'Raw - Workforce'!E30 -> 0 | K56: =IFERROR('Raw - Workforce'!K30/'Raw - Workforce'!G30,0) -> 0
A57: ='Raw - Workforce'!A34 -> Location 2 | B57: ='Raw - Workforce'!B34 -> Position G | C57: ='Raw - Workforce'!G34+'Raw - Workforce'!K34 -> 0 | D57: ='Raw - Workforce'!H34+'Raw - Workforce'!L34 -> 0 | E57: ='Raw - Workforce'!I34+'Raw - Workforce'!M34 -> 0 | F57: ='Raw - Workforce'!J34+'Raw - Workforce'!N34 -> 0 | G57: =C57-E57 -> 0 | H57: =IFERROR(G57/E57,0) -> 0 | I57: =C57-D57 -> 0 | J57: ='Raw - Workforce'!C34-'Raw - Workforce'!E34 -> 0 | K57: =IFERROR('Raw - Workforce'!K34/'Raw - Workforce'!G34,0) -> 0
A58: ='Raw - Workforce'!A37 -> Location 2 | B58: ='Raw - Workforce'!B37 -> Position J | C58: ='Raw - Workforce'!G37+'Raw - Workforce'!K37 -> 0 | D58: ='Raw - Workforce'!H37+'Raw - Workforce'!L37 -> 0 | E58: ='Raw - Workforce'!I37+'Raw - Workforce'!M37 -> 0 | F58: ='Raw - Workforce'!J37+'Raw - Workforce'!N37 -> 0 | G58: =C58-E58 -> 0 | H58: =IFERROR(G58/E58,0) -> 0 | I58: =C58-D58 -> 0 | J58: ='Raw - Workforce'!C37-'Raw - Workforce'!E37 -> 0 | K58: =IFERROR('Raw - Workforce'!K37/'Raw - Workforce'!G37,0) -> 0
A59: ='Raw - Workforce'!A53 -> Location 2 | B59: ='Raw - Workforce'!B53 -> Position Z | C59: ='Raw - Workforce'!G53+'Raw - Workforce'!K53 -> 0 | D59: ='Raw - Workforce'!H53+'Raw - Workforce'!L53 -> 0 | E59: ='Raw - Workforce'!I53+'Raw - Workforce'!M53 -> 0 | F59: ='Raw - Workforce'!J53+'Raw - Workforce'!N53 -> 0 | G59: =C59-E59 -> 0 | H59: =IFERROR(G59/E59,0) -> 0 | I59: =C59-D59 -> 0 | J59: ='Raw - Workforce'!C53-'Raw - Workforce'!E53 -> 0 | K59: =IFERROR('Raw - Workforce'!K53/'Raw - Workforce'!G53,0) -> 0
A60: ='Raw - Workforce'!A56 -> Location 3 | B60: ='Raw - Workforce'!B56 -> Position C | C60: ='Raw - Workforce'!G56+'Raw - Workforce'!K56 -> 0 | D60: ='Raw - Workforce'!H56+'Raw - Workforce'!L56 -> 0 | E60: ='Raw - Workforce'!I56+'Raw - Workforce'!M56 -> 0 | F60: ='Raw - Workforce'!J56+'Raw - Workforce'!N56 -> 0 | G60: =C60-E60 -> 0 | H60: =IFERROR(G60/E60,0) -> 0 | I60: =C60-D60 -> 0 | J60: ='Raw - Workforce'!C56-'Raw - Workforce'!E56 -> 0 | K60: =IFERROR('Raw - Workforce'!K56/'Raw - Workforce'!G56,0) -> 0
A61: ='Raw - Workforce'!A60 -> Location 3 | B61: ='Raw - Workforce'!B60 -> Position G | C61: ='Raw - Workforce'!G60+'Raw - Workforce'!K60 -> 0 | D61: ='Raw - Workforce'!H60+'Raw - Workforce'!L60 -> 0 | E61: ='Raw - Workforce'!I60+'Raw - Workforce'!M60 -> 0 | F61: ='Raw - Workforce'!J60+'Raw - Workforce'!N60 -> 0 | G61: =C61-E61 -> 0 | H61: =IFERROR(G61/E61,0) -> 0 | I61: =C61-D61 -> 0 | J61: ='Raw - Workforce'!C60-'Raw - Workforce'!E60 -> 0 | K61: =IFERROR('Raw - Workforce'!K60/'Raw - Workforce'!G60,0) -> 0
A62: ='Raw - Workforce'!A63 -> Location 3 | B62: ='Raw - Workforce'!B63 -> Position J | C62: ='Raw - Workforce'!G63+'Raw - Workforce'!K63 -> 0 | D62: ='Raw - Workforce'!H63+'Raw - Workforce'!L63 -> 0 | E62: ='Raw - Workforce'!I63+'Raw - Workforce'!M63 -> 0 | F62: ='Raw - Workforce'!J63+'Raw - Workforce'!N63 -> 0 | G62: =C62-E62 -> 0 | H62: =IFERROR(G62/E62,0) -> 0 | I62: =C62-D62 -> 0 | J62: ='Raw - Workforce'!C63-'Raw - Workforce'!E63 -> 0 | K62: =IFERROR('Raw - Workforce'!K63/'Raw - Workforce'!G63,0) -> 0
A63: ='Raw - Workforce'!A78 -> Location 3 | B63: ='Raw - Workforce'!B78 -> Position Y | C63: ='Raw - Workforce'!G78+'Raw - Workforce'!K78 -> 0 | D63: ='Raw - Workforce'!H78+'Raw - Workforce'!L78 -> 0 | E63: ='Raw - Workforce'!I78+'Raw - Workforce'!M78 -> 0 | F63: ='Raw - Workforce'!J78+'Raw - Workforce'!N78 -> 0 | G63: =C63-E63 -> 0 | H63: =IFERROR(G63/E63,0) -> 0 | I63: =C63-D63 -> 0 | J63: ='Raw - Workforce'!C78-'Raw - Workforce'!E78 -> 0 | K63: =IFERROR('Raw - Workforce'!K78/'Raw - Workforce'!G78,0) -> 0
A64: ='Raw - Workforce'!A79 -> Location 3 | B64: ='Raw - Workforce'!B79 -> Position Z | C64: ='Raw - Workforce'!G79+'Raw - Workforce'!K79 -> 0 | D64: ='Raw - Workforce'!H79+'Raw - Workforce'!L79 -> 0 | E64: ='Raw - Workforce'!I79+'Raw - Workforce'!M79 -> 0 | F64: ='Raw - Workforce'!J79+'Raw - Workforce'!N79 -> 0 | G64: =C64-E64 -> 0 | H64: =IFERROR(G64/E64,0) -> 0 | I64: =C64-D64 -> 0 | J64: ='Raw - Workforce'!C79-'Raw - Workforce'!E79 -> 0 | K64: =IFERROR('Raw - Workforce'!K79/'Raw - Workforce'!G79,0) -> 0
A65: ='Raw - Workforce'!A82 -> Location 4 | B65: ='Raw - Workforce'!B82 -> Position C | C65: ='Raw - Workforce'!G82+'Raw - Workforce'!K82 -> 0 | D65: ='Raw - Workforce'!H82+'Raw - Workforce'!L82 -> 0 | E65: ='Raw - Workforce'!I82+'Raw - Workforce'!M82 -> 0 | F65: ='Raw - Workforce'!J82+'Raw - Workforce'!N82 -> 0 | G65: =C65-E65 -> 0 | H65: =IFERROR(G65/E65,0) -> 0 | I65: =C65-D65 -> 0 | J65: ='Raw - Workforce'!C82-'Raw - Workforce'!E82 -> 0 | K65: =IFERROR('Raw - Workforce'!K82/'Raw - Workforce'!G82,0) -> 0
A66: ='Raw - Workforce'!A102 -> Location 4 | B66: ='Raw - Workforce'!B102 -> Position W | C66: ='Raw - Workforce'!G102+'Raw - Workforce'!K102 -> 10445.283 | D66: ='Raw - Workforce'!H102+'Raw - Workforce'!L102 -> 10445.283 | E66: ='Raw - Workforce'!I102+'Raw - Workforce'!M102 -> 10445.283 | F66: ='Raw - Workforce'!J102+'Raw - Workforce'!N102 -> 144592.96 | G66: =C66-E66 -> 0 | H66: =IFERROR(G66/E66,0) -> 0 | I66: =C66-D66 -> 0 | J66: ='Raw - Workforce'!C102-'Raw - Workforce'!E102 -> 0 | K66: =IFERROR('Raw - Workforce'!K102/'Raw - Workforce'!G102,0) -> 0
A67: ='Raw - Workforce'!A104 -> Location 4 | B67: ='Raw - Workforce'!B104 -> Position Y | C67: ='Raw - Workforce'!G104+'Raw - Workforce'!K104 -> 0 | D67: ='Raw - Workforce'!H104+'Raw - Workforce'!L104 -> 0 | E67: ='Raw - Workforce'!I104+'Raw - Workforce'!M104 -> 0 | F67: ='Raw - Workforce'!J104+'Raw - Workforce'!N104 -> 0 | G67: =C67-E67 -> 0 | H67: =IFERROR(G67/E67,0) -> 0 | I67: =C67-D67 -> 0 | J67: ='Raw - Workforce'!C104-'Raw - Workforce'!E104 -> 0 | K67: =IFERROR('Raw - Workforce'!K104/'Raw - Workforce'!G104,0) -> 0
A68: ='Raw - Workforce'!A105 -> Location 4 | B68: ='Raw - Workforce'!B105 -> Position Z | C68: ='Raw - Workforce'!G105+'Raw - Workforce'!K105 -> 0 | D68: ='Raw - Workforce'!H105+'Raw - Workforce'!L105 -> 0 | E68: ='Raw - Workforce'!I105+'Raw - Workforce'!M105 -> 0 | F68: ='Raw - Workforce'!J105+'Raw - Workforce'!N105 -> 0 | G68: =C68-E68 -> 0 | H68: =IFERROR(G68/E68,0) -> 0 | I68: =C68-D68 -> 0 | J68: ='Raw - Workforce'!C105-'Raw - Workforce'!E105 -> 0 | K68: =IFERROR('Raw - Workforce'!K105/'Raw - Workforce'!G105,0) -> 0
A69: ='Raw - Workforce'!A89 -> Location 4 | B69: ='Raw - Workforce'!B89 -> Position J | C69: ='Raw - Workforce'!G89+'Raw - Workforce'!K89 -> 27306.934 | D69: ='Raw - Workforce'!H89+'Raw - Workforce'!L89 -> 27306.934 | E69: ='Raw - Workforce'!I89+'Raw - Workforce'!M89 -> 26457.934 | F69: ='Raw - Workforce'!J89+'Raw - Workforce'!N89 -> 32340.69 | G69: =C69-E69 -> 849 | H69: =IFERROR(G69/E69,0) -> 0.032088674 | I69: =C69-D69 -> 0 | J69: ='Raw - Workforce'!C89-'Raw - Workforce'!E89 -> -0.5 | K69: =IFERROR('Raw - Workforce'!K89/'Raw - Workforce'!G89,0) -> 0.0064870602
A70: ='Raw - Workforce'!A92 -> Location 4 | B70: ='Raw - Workforce'!B92 -> Position M | C70: ='Raw - Workforce'!G92+'Raw - Workforce'!K92 -> 205891.08 | D70: ='Raw - Workforce'!H92+'Raw - Workforce'!L92 -> 209568.96 | E70: ='Raw - Workforce'!I92+'Raw - Workforce'!M92 -> 204891.08 | F70: ='Raw - Workforce'!J92+'Raw - Workforce'!N92 -> 259054.87 | G70: =C70-E70 -> 1000 | H70: =IFERROR(G70/E70,0) -> 0.0048806419 | I70: =C70-D70 -> -3677.8784 | J70: ='Raw - Workforce'!C92-'Raw - Workforce'!E92 -> 5.1966667 | K70: =IFERROR('Raw - Workforce'!K92/'Raw - Workforce'!G92,0) -> 0.063197358
A71: ='Raw - Workforce'!A86 -> Location 4 | B71: ='Raw - Workforce'!B86 -> Position G | C71: ='Raw - Workforce'!G86+'Raw - Workforce'!K86 -> 14177.419 | D71: ='Raw - Workforce'!H86+'Raw - Workforce'!L86 -> 14177.419 | E71: ='Raw - Workforce'!I86+'Raw - Workforce'!M86 -> 12074.419 | F71: ='Raw - Workforce'!J86+'Raw - Workforce'!N86 -> 26290.62 | G71: =C71-E71 -> 2103 | H71: =IFERROR(G71/E71,0) -> 0.17416987 | I71: =C71-D71 -> 0 | J71: ='Raw - Workforce'!C86-'Raw - Workforce'!E86 -> 0.2 | K71: =IFERROR('Raw - Workforce'!K86/'Raw - Workforce'!G86,0) -> 0.0046389748
A72: ='Raw - Workforce'!A91 -> Location 4 | B72: ='Raw - Workforce'!B91 -> Position L | C72: ='Raw - Workforce'!G91+'Raw - Workforce'!K91 -> 1908097 | D72: ='Raw - Workforce'!H91+'Raw - Workforce'!L91 -> 1828716.8 | E72: ='Raw - Workforce'!I91+'Raw - Workforce'!M91 -> 1904267.1 | F72: ='Raw - Workforce'!J91+'Raw - Workforce'!N91 -> 1731166.4 | G72: =C72-E72 -> 3829.8305 | H72: =IFERROR(G72/E72,0) -> 0.0020111834 | I72: =C72-D72 -> 79380.187 | J72: ='Raw - Workforce'!C91-'Raw - Workforce'!E91 -> -37.4 | K72: =IFERROR('Raw - Workforce'!K91/'Raw - Workforce'!G91,0) -> 0.082138616
A73: ='Raw - Workforce'!A41 -> Location 2 | B73: ='Raw - Workforce'!B41 -> Position N | C73: ='Raw - Workforce'!G41+'Raw - Workforce'!K41 -> 150728.5 | D73: ='Raw - Workforce'!H41+'Raw - Workforce'!L41 -> 154521.87 | E73: ='Raw - Workforce'!I41+'Raw - Workforce'!M41 -> 145036.78 | F73: ='Raw - Workforce'!J41+'Raw - Workforce'!N41 -> 153249.11 | G73: =C73-E73 -> 5691.7195 | H73: =IFERROR(G73/E73,0) -> 0.039243284 | I73: =C73-D73 -> -3793.3671 | J73: ='Raw - Workforce'!C41-'Raw - Workforce'!E41 -> -0.48008256 | K73: =IFERROR('Raw - Workforce'!K41/'Raw - Workforce'!G41,0) -> 0.20837116
A74: ='Raw - Workforce'!A17 -> Location 1 | B74: ='Raw - Workforce'!B17 -> Position P | C74: ='Raw - Workforce'!G17+'Raw - Workforce'!K17 -> 434030.35 | D74: ='Raw - Workforce'!H17+'Raw - Workforce'!L17 -> 434030.35 | E74: ='Raw - Workforce'!I17+'Raw - Workforce'!M17 -> 428101.38 | F74: ='Raw - Workforce'!J17+'Raw - Workforce'!N17 -> 434208.23 | G74: =C74-E74 -> 5928.9768 | H74: =IFERROR(G74/E74,0) -> 0.013849469 | I74: =C74-D74 -> 0 | J74: ='Raw - Workforce'!C17-'Raw - Workforce'!E17 -> 5.6962067 | K74: =IFERROR('Raw - Workforce'!K17/'Raw - Workforce'!G17,0) -> 0.136959
A75: ='Raw - Workforce'!A18 -> Location 1 | B75: ='Raw - Workforce'!B18 -> Position Q | C75: ='Raw - Workforce'!G18+'Raw - Workforce'!K18 -> 28489.166 | D75: ='Raw - Workforce'!H18+'Raw - Workforce'!L18 -> 28489.166 | E75: ='Raw - Workforce'!I18+'Raw - Workforce'!M18 -> 22429.332 | F75: ='Raw - Workforce'!J18+'Raw - Workforce'!N18 -> 29615.49 | G75: =C75-E75 -> 6059.8344 | H75: =IFERROR(G75/E75,0) -> 0.27017454 | I75: =C75-D75 -> 0 | J75: ='Raw - Workforce'!C18-'Raw - Workforce'!E18 -> 1.63 | K75: =IFERROR('Raw - Workforce'!K18/'Raw - Workforce'!G18,0) -> 0.06808357
A76: ='Raw - Workforce'!A42 -> Location 2 | B76: ='Raw - Workforce'!B42 -> Position O | C76: ='Raw - Workforce'!G42+'Raw - Workforce'!K42 -> 266548.21 | D76: ='Raw - Workforce'!H42+'Raw - Workforce'!L42 -> 301747.59 | E76: ='Raw - Workforce'!I42+'Raw - Workforce'!M42 -> 260396.3 | F76: ='Raw - Workforce'!J42+'Raw - Workforce'!N42 -> 246437.23 | G76: =C76-E76 -> 6151.9144 | H76: =IFERROR(G76/E76,0) -> 0.023625199 | I76: =C76-D76 -> -35199.377 | J76: ='Raw - Workforce'!C42-'Raw - Workforce'!E42 -> 0.44403653 | K76: =IFERROR('Raw - Workforce'!K42/'Raw - Workforce'!G42,0) -> 0.18242731
A77: ='Raw - Workforce'!A66 -> Location 3 | B77: ='Raw - Workforce'!B66 -> Position M | C77: ='Raw - Workforce'!G66+'Raw - Workforce'!K66 -> 198153.98 | D77: ='Raw - Workforce'!H66+'Raw - Workforce'!L66 -> 196950.39 | E77: ='Raw - Workforce'!I66+'Raw - Workforce'!M66 -> 191569.57 | F77: ='Raw - Workforce'!J66+'Raw - Workforce'!N66 -> 181355.17 | G77: =C77-E77 -> 6584.4097 | H77: =IFERROR(G77/E77,0) -> 0.034370853 | I77: =C77-D77 -> 1203.5894 | J77: ='Raw - Workforce'!C66-'Raw - Workforce'!E66 -> 6.9991667 | K77: =IFERROR('Raw - Workforce'!K66/'Raw - Workforce'!G66,0) -> 0.14877257
A78: ='Raw - Workforce'!A15 -> Location 1 | B78: ='Raw - Workforce'!B15 -> Position N | C78: ='Raw - Workforce'!G15+'Raw - Workforce'!K15 -> 125542.45 | D78: ='Raw - Workforce'!H15+'Raw - Workforce'!L15 -> 125542.45 | E78: ='Raw - Workforce'!I15+'Raw - Workforce'!M15 -> 118030.33 | F78: ='Raw - Workforce'!J15+'Raw - Workforce'!N15 -> 126202.79 | G78: =C78-E78 -> 7512.1188 | H78: =IFERROR(G78/E78,0) -> 0.063645663 | I78: =C78-D78 -> 0 | J78: ='Raw - Workforce'!C15-'Raw - Workforce'!E15 -> -0.31645811 | K78: =IFERROR('Raw - Workforce'!K15/'Raw - Workforce'!G15,0) -> 0.084088485
A79: ='Raw - Workforce'!A14 -> Location 1 | B79: ='Raw - Workforce'!B14 -> Position M | C79: ='Raw - Workforce'!G14+'Raw - Workforce'!K14 -> 114442.75 | D79: ='Raw - Workforce'!H14+'Raw - Workforce'!L14 -> 114442.75 | E79: ='Raw - Workforce'!I14+'Raw - Workforce'!M14 -> 106479.71 | F79: ='Raw - Workforce'!J14+'Raw - Workforce'!N14 -> 137557.93 | G79: =C79-E79 -> 7963.0451 | H79: =IFERROR(G79/E79,0) -> 0.074784625 | I79: =C79-D79 -> 0 | J79: ='Raw - Workforce'!C14-'Raw - Workforce'!E14 -> -3.1856208 | K79: =IFERROR('Raw - Workforce'!K14/'Raw - Workforce'!G14,0) -> 0.09469484
A80: ='Raw - Workforce'!A68 -> Location 3 | B80: ='Raw - Workforce'!B68 -> Position O | C80: ='Raw - Workforce'!G68+'Raw - Workforce'!K68 -> 263568.77 | D80: ='Raw - Workforce'!H68+'Raw - Workforce'!L68 -> 282160.53 | E80: ='Raw - Workforce'!I68+'Raw - Workforce'!M68 -> 253369.1 | F80: ='Raw - Workforce'!J68+'Raw - Workforce'!N68 -> 326565.9 | G80: =C80-E80 -> 10199.67 | H80: =IFERROR(G80/E80,0) -> 0.040256173 | I80: =C80-D80 -> -18591.759 | J80: ='Raw - Workforce'!C68-'Raw - Workforce'!E68 -> -7.3686547 | K80: =IFERROR('Raw - Workforce'!K68/'Raw - Workforce'!G68,0) -> 0.092254634
A81: ='Raw - Workforce'!A46 -> Location 2 | B81: ='Raw - Workforce'!B46 -> Position S | C81: ='Raw - Workforce'!G46+'Raw - Workforce'!K46 -> 257812.5 | D81: ='Raw - Workforce'!H46+'Raw - Workforce'!L46 -> 246806.4 | E81: ='Raw - Workforce'!I46+'Raw - Workforce'!M46 -> 247554.34 | F81: ='Raw - Workforce'!J46+'Raw - Workforce'!N46 -> 243641.03 | G81: =C81-E81 -> 10258.156 | H81: =IFERROR(G81/E81,0) -> 0.041437996 | I81: =C81-D81 -> 11006.1 | J81: ='Raw - Workforce'!C46-'Raw - Workforce'!E46 -> -1.421 | K81: =IFERROR('Raw - Workforce'!K46/'Raw - Workforce'!G46,0) -> 0
A82: ='Raw - Workforce'!A90 -> Location 4 | B82: ='Raw - Workforce'!B90 -> Position K | C82: ='Raw - Workforce'!G90+'Raw - Workforce'!K90 -> 772021.51 | D82: ='Raw - Workforce'!H90+'Raw - Workforce'!L90 -> 745059.51 | E82: ='Raw - Workforce'!I90+'Raw - Workforce'!M90 -> 759021.51 | F82: ='Raw - Workforce'!J90+'Raw - Workforce'!N90 -> 756269.84 | G82: =C82-E82 -> 13000 | H82: =IFERROR(G82/E82,0) -> 0.017127314 | I82: =C82-D82 -> 26962 | J82: ='Raw - Workforce'!C90-'Raw - Workforce'!E90 -> -16 | K82: =IFERROR('Raw - Workforce'!K90/'Raw - Workforce'!G90,0) -> 0.11351871
A83: ='Raw - Workforce'!A75 -> Location 3 | B83: ='Raw - Workforce'!B75 -> Position V | C83: ='Raw - Workforce'!G75+'Raw - Workforce'!K75 -> 197458.16 | D83: ='Raw - Workforce'!H75+'Raw - Workforce'!L75 -> 197458.16 | E83: ='Raw - Workforce'!I75+'Raw - Workforce'!M75 -> 182493.72 | F83: ='Raw - Workforce'!J75+'Raw - Workforce'!N75 -> 179905.12 | G83: =C83-E83 -> 14964.437 | H83: =IFERROR(G83/E83,0) -> 0.081999735 | I83: =C83-D83 -> 0 | J83: ='Raw - Workforce'!C75-'Raw - Workforce'!E75 -> 1.42 | K83: =IFERROR('Raw - Workforce'!K75/'Raw - Workforce'!G75,0) -> 0
A84: ='Raw - Workforce'!A36 -> Location 2 | B84: ='Raw - Workforce'!B36 -> Position I | C84: ='Raw - Workforce'!G36+'Raw - Workforce'!K36 -> 115543.83 | D84: ='Raw - Workforce'!H36+'Raw - Workforce'!L36 -> 114152.93 | E84: ='Raw - Workforce'!I36+'Raw - Workforce'!M36 -> 99170.396 | F84: ='Raw - Workforce'!J36+'Raw - Workforce'!N36 -> 90146.44 | G84: =C84-E84 -> 16373.43 | H84: =IFERROR(G84/E84,0) -> 0.16510401 | I84: =C84-D84 -> 1390.8962 | J84: ='Raw - Workforce'!C36-'Raw - Workforce'!E36 -> 5.3 | K84: =IFERROR('Raw - Workforce'!K36/'Raw - Workforce'!G36,0) -> 0.10491598
A85: ='Raw - Workforce'!A45 -> Location 2 | B85: ='Raw - Workforce'!B45 -> Position R | C85: ='Raw - Workforce'!G45+'Raw - Workforce'!K45 -> 69469.912 | D85: ='Raw - Workforce'!H45+'Raw - Workforce'!L45 -> 62811.912 | E85: ='Raw - Workforce'!I45+'Raw - Workforce'!M45 -> 52085.814 | F85: ='Raw - Workforce'!J45+'Raw - Workforce'!N45 -> 57997.94 | G85: =C85-E85 -> 17384.098 | H85: =IFERROR(G85/E85,0) -> 0.33375878 | I85: =C85-D85 -> 6658 | J85: ='Raw - Workforce'!C45-'Raw - Workforce'!E45 -> 4.8260785 | K85: =IFERROR('Raw - Workforce'!K45/'Raw - Workforce'!G45,0) -> 0.15289495
A86: ='Raw - Workforce'!A74 -> Location 3 | B86: ='Raw - Workforce'!B74 -> Position U | C86: ='Raw - Workforce'!G74+'Raw - Workforce'!K74 -> 331797.69 | D86: ='Raw - Workforce'!H74+'Raw - Workforce'!L74 -> 331797.69 | E86: ='Raw - Workforce'!I74+'Raw - Workforce'!M74 -> 313490.65 | F86: ='Raw - Workforce'!J74+'Raw - Workforce'!N74 -> 250645.58 | G86: =C86-E86 -> 18307.045 | H86: =IFERROR(G86/E86,0) -> 0.05839742 | I86: =C86-D86 -> 0 | J86: ='Raw - Workforce'!C74-'Raw - Workforce'!E74 -> 1.55 | K86: =IFERROR('Raw - Workforce'!K74/'Raw - Workforce'!G74,0) -> 0
A87: ='Raw - Workforce'!A47 -> Location 2 | B87: ='Raw - Workforce'!B47 -> Position T | C87: ='Raw - Workforce'!G47+'Raw - Workforce'!K47 -> 1279727.1 | D87: ='Raw - Workforce'!H47+'Raw - Workforce'!L47 -> 1307958.8 | E87: ='Raw - Workforce'!I47+'Raw - Workforce'!M47 -> 1260720.1 | F87: ='Raw - Workforce'!J47+'Raw - Workforce'!N47 -> 1254842.4 | G87: =C87-E87 -> 19007.009 | H87: =IFERROR(G87/E87,0) -> 0.015076312 | I87: =C87-D87 -> -28231.711 | J87: ='Raw - Workforce'!C47-'Raw - Workforce'!E47 -> -5.6585332 | K87: =IFERROR('Raw - Workforce'!K47/'Raw - Workforce'!G47,0) -> 0.11852068
A88: ='Raw - Workforce'!A58 -> Location 3 | B88: ='Raw - Workforce'!B58 -> Position E | C88: ='Raw - Workforce'!G58+'Raw - Workforce'!K58 -> 26121.669 | D88: ='Raw - Workforce'!H58+'Raw - Workforce'!L58 -> 23077.739 | E88: ='Raw - Workforce'!I58+'Raw - Workforce'!M58 -> 6737.2227 | F88: ='Raw - Workforce'!J58+'Raw - Workforce'!N58 -> 12667 | G88: =C88-E88 -> 19384.446 | H88: =IFERROR(G88/E88,0) -> 2.8772161 | I88: =C88-D88 -> 3043.9296 | J88: ='Raw - Workforce'!C58-'Raw - Workforce'!E58 -> 4.6443702 | K88: =IFERROR('Raw - Workforce'!K58/'Raw - Workforce'!G58,0) -> 0.11911228
A89: ='Raw - Workforce'!A67 -> Location 3 | B89: ='Raw - Workforce'!B67 -> Position N | C89: ='Raw - Workforce'!G67+'Raw - Workforce'!K67 -> 198027.71 | D89: ='Raw - Workforce'!H67+'Raw - Workforce'!L67 -> 198683.17 | E89: ='Raw - Workforce'!I67+'Raw - Workforce'!M67 -> 178449.74 | F89: ='Raw - Workforce'!J67+'Raw - Workforce'!N67 -> 197621.76 | G89: =C89-E89 -> 19577.976 | H89: =IFERROR(G89/E89,0) -> 0.10971143 | I89: =C89-D89 -> -655.46158 | J89: ='Raw - Workforce'!C67-'Raw - Workforce'!E67 -> 0.95916667 | K89: =IFERROR('Raw - Workforce'!K67/'Raw - Workforce'!G67,0) -> 0.11775848
A90: ='Raw - Workforce'!A59 -> Location 3 | B90: ='Raw - Workforce'!B59 -> Position F | C90: ='Raw - Workforce'!G59+'Raw - Workforce'!K59 -> 40050.518 | D90: ='Raw - Workforce'!H59+'Raw - Workforce'!L59 -> 41652.538 | E90: ='Raw - Workforce'!I59+'Raw - Workforce'!M59 -> 19131.825 | F90: ='Raw - Workforce'!J59+'Raw - Workforce'!N59 -> 13445.28 | G90: =C90-E90 -> 20918.693 | H90: =IFERROR(G90/E90,0) -> 1.0933976 | I90: =C90-D90 -> -1602.0207 | J90: ='Raw - Workforce'!C59-'Raw - Workforce'!E59 -> 7.17 | K90: =IFERROR('Raw - Workforce'!K59/'Raw - Workforce'!G59,0) -> 0.11910209
A91: ='Raw - Workforce'!A32 -> Location 2 | B91: ='Raw - Workforce'!B32 -> Position E | C91: ='Raw - Workforce'!G32+'Raw - Workforce'!K32 -> 124442.62 | D91: ='Raw - Workforce'!H32+'Raw - Workforce'!L32 -> 124442.62 | E91: ='Raw - Workforce'!I32+'Raw - Workforce'!M32 -> 102515.38 | F91: ='Raw - Workforce'!J32+'Raw - Workforce'!N32 -> 109955.78 | G91: =C91-E91 -> 21927.233 | H91: =IFERROR(G91/E91,0) -> 0.21389212 | I91: =C91-D91 -> 0 | J91: ='Raw - Workforce'!C32-'Raw - Workforce'!E32 -> 6.04 | K91: =IFERROR('Raw - Workforce'!K32/'Raw - Workforce'!G32,0) -> 0.068174491
A92: ='Raw - Workforce'!A71 -> Location 3 | B92: ='Raw - Workforce'!B71 -> Position R | C92: ='Raw - Workforce'!G71+'Raw - Workforce'!K71 -> 150267.69 | D92: ='Raw - Workforce'!H71+'Raw - Workforce'!L71 -> 150267.69 | E92: ='Raw - Workforce'!I71+'Raw - Workforce'!M71 -> 125745.06 | F92: ='Raw - Workforce'!J71+'Raw - Workforce'!N71 -> 98598.43 | G92: =C92-E92 -> 24522.63 | H92: =IFERROR(G92/E92,0) -> 0.19501863 | I92: =C92-D92 -> 0 | J92: ='Raw - Workforce'!C71-'Raw - Workforce'!E71 -> 13 | K92: =IFERROR('Raw - Workforce'!K71/'Raw - Workforce'!G71,0) -> 0.038867641
A93: ='Raw - Workforce'!A93 -> Location 4 | B93: ='Raw - Workforce'!B93 -> Position N | C93: ='Raw - Workforce'!G93+'Raw - Workforce'!K93 -> 369580.42 | D93: ='Raw - Workforce'!H93+'Raw - Workforce'!L93 -> 367580.42 | E93: ='Raw - Workforce'!I93+'Raw - Workforce'!M93 -> 345037.9 | F93: ='Raw - Workforce'!J93+'Raw - Workforce'!N93 -> 330049.91 | G93: =C93-E93 -> 24542.518 | H93: =IFERROR(G93/E93,0) -> 0.071129918 | I93: =C93-D93 -> 2000 | J93: ='Raw - Workforce'!C93-'Raw - Workforce'!E93 -> 1.1775 | K93: =IFERROR('Raw - Workforce'!K93/'Raw - Workforce'!G93,0) -> 0.15231488
A94: ='Raw - Workforce'!A35 -> Location 2 | B94: ='Raw - Workforce'!B35 -> Position H | C94: ='Raw - Workforce'!G35+'Raw - Workforce'!K35 -> 834644.42 | D94: ='Raw - Workforce'!H35+'Raw - Workforce'!L35 -> 815506.41 | E94: ='Raw - Workforce'!I35+'Raw - Workforce'!M35 -> 808116.49 | F94: ='Raw - Workforce'!J35+'Raw - Workforce'!N35 -> 708649.9 | G94: =C94-E94 -> 26527.926 | H94: =IFERROR(G94/E94,0) -> 0.03282686 | I94: =C94-D94 -> 19138.004 | J94: ='Raw - Workforce'!C35-'Raw - Workforce'!E35 -> 9.8 | K94: =IFERROR('Raw - Workforce'!K35/'Raw - Workforce'!G35,0) -> 0.07625404
A95: ='Raw - Workforce'!A9 -> Location 1 | B95: ='Raw - Workforce'!B9 -> Position H | C95: ='Raw - Workforce'!G9+'Raw - Workforce'!K9 -> 711646.16 | D95: ='Raw - Workforce'!H9+'Raw - Workforce'!L9 -> 695743.38 | E95: ='Raw - Workforce'!I9+'Raw - Workforce'!M9 -> 684432.03 | F95: ='Raw - Workforce'!J9+'Raw - Workforce'!N9 -> 629599.17 | G95: =C95-E95 -> 27214.13 | H95: =IFERROR(G95/E95,0) -> 0.039761625 | I95: =C95-D95 -> 15902.779 | J95: ='Raw - Workforce'!C9-'Raw - Workforce'!E9 -> 10.774831 | K95: =IFERROR('Raw - Workforce'!K9/'Raw - Workforce'!G9,0) -> 0.13740779
A96: ='Raw - Workforce'!A76 -> Location 3 | B96: ='Raw - Workforce'!B76 -> Position W | C96: ='Raw - Workforce'!G76+'Raw - Workforce'!K76 -> 135786.1 | D96: ='Raw - Workforce'!H76+'Raw - Workforce'!L76 -> 140723.78 | E96: ='Raw - Workforce'!I76+'Raw - Workforce'!M76 -> 107476.32 | F96: ='Raw - Workforce'!J76+'Raw - Workforce'!N76 -> 191737.91 | G96: =C96-E96 -> 28309.783 | H96: =IFERROR(G96/E96,0) -> 0.26340485 | I96: =C96-D96 -> -4937.6764 | J96: ='Raw - Workforce'!C76-'Raw - Workforce'!E76 -> 9.52 | K96: =IFERROR('Raw - Workforce'!K76/'Raw - Workforce'!G76,0) -> 0.19994634
A97: ='Raw - Workforce'!A98 -> Location 4 | B97: ='Raw - Workforce'!B98 -> Position S | C97: ='Raw - Workforce'!G98+'Raw - Workforce'!K98 -> 368071.62 | D97: ='Raw - Workforce'!H98+'Raw - Workforce'!L98 -> 366071.62 | E97: ='Raw - Workforce'!I98+'Raw - Workforce'!M98 -> 336810.4 | F97: ='Raw - Workforce'!J98+'Raw - Workforce'!N98 -> 299281.08 | G97: =C97-E97 -> 31261.215 | H97: =IFERROR(G97/E97,0) -> 0.092815468 | I97: =C97-D97 -> 2000 | J97: ='Raw - Workforce'!C98-'Raw - Workforce'!E98 -> 4.2 | K97: =IFERROR('Raw - Workforce'!K98/'Raw - Workforce'!G98,0) -> 0
A98: ='Raw - Workforce'!A48 -> Location 2 | B98: ='Raw - Workforce'!B48 -> Position U | C98: ='Raw - Workforce'!G48+'Raw - Workforce'!K48 -> 202357.83 | D98: ='Raw - Workforce'!H48+'Raw - Workforce'!L48 -> 164849.23 | E98: ='Raw - Workforce'!I48+'Raw - Workforce'!M48 -> 161886.26 | F98: ='Raw - Workforce'!J48+'Raw - Workforce'!N48 -> 312663.29 | G98: =C98-E98 -> 40471.565 | H98: =IFERROR(G98/E98,0) -> 0.25 | I98: =C98-D98 -> 37508.6 | J98: ='Raw - Workforce'!C48-'Raw - Workforce'!E48 -> 3.5 | K98: =IFERROR('Raw - Workforce'!K48/'Raw - Workforce'!G48,0) -> 0
A99: ='Raw - Workforce'!A94 -> Location 4 | B99: ='Raw - Workforce'!B94 -> Position O | C99: ='Raw - Workforce'!G94+'Raw - Workforce'!K94 -> 314685.07 | D99: ='Raw - Workforce'!H94+'Raw - Workforce'!L94 -> 326685.55 | E99: ='Raw - Workforce'!I94+'Raw - Workforce'!M94 -> 273965.4 | F99: ='Raw - Workforce'!J94+'Raw - Workforce'!N94 -> 285391.58 | G99: =C99-E99 -> 40719.675 | H99: =IFERROR(G99/E99,0) -> 0.14863072 | I99: =C99-D99 -> -12000.477 | J99: ='Raw - Workforce'!C94-'Raw - Workforce'!E94 -> 4.1944833 | K99: =IFERROR('Raw - Workforce'!K94/'Raw - Workforce'!G94,0) -> 0.12561243
A100: ='Raw - Workforce'!A99 -> Location 4 | B100: ='Raw - Workforce'!B99 -> Position T | C100: ='Raw - Workforce'!G99+'Raw - Workforce'!K99 -> 2256338 | D100: ='Raw - Workforce'!H99+'Raw - Workforce'!L99 -> 2285016.4 | E100: ='Raw - Workforce'!I99+'Raw - Workforce'!M99 -> 2215244.2 | F100: ='Raw - Workforce'!J99+'Raw - Workforce'!N99 -> 2144592.1 | G100: =C100-E100 -> 41093.844 | H100: =IFERROR(G100/E100,0) -> 0.01855048 | I100: =C100-D100 -> -28678.355 | J100: ='Raw - Workforce'!C99-'Raw - Workforce'!E99 -> 2.5703167 | K100: =IFERROR('Raw - Workforce'!K99/'Raw - Workforce'!G99,0) -> 0.077708217
...

Sheet Raw - Workforce
A1: Location | B1: Position | C1: FTE Cur.Fcst | D1: FTE Prior Fcst | E1: FTE Plan | F1: FTE Actual 2025 | G1: Salary $ Cur.Fcst | H1: Salary $ Prior Fcst | I1: Salary $ Plan | J1: Salary $ Actual 2025 | K1: OT $ Cur.Fcst | L1: OT $ Prior Fcst | M1: OT $ Plan | N1: OT $ Actual 2025
A2: Location 1 | B2: Position A | C2: 332.54194 | D2: 332.87073 | E2: 349.82814 | F2: 345.88 | G2: 1111060.1 | H2: 1114823.5 | I2: 1100596.5 | J2: 1067045.8 | K2: 203565.12 | L2: 203565.12 | M2: 239368.89 | N2: 216881.04
A3: Location 1 | B3: Position B | C3: 408.85126 | D3: 431.64203 | E3: 453.52454 | F3: 410.64 | G3: 1362557.9 | H3: 1385503.7 | I3: 1301697.3 | J3: 1126091.5 | K3: 287593.12 | L3: 287593.12 | M3: 376503.1 | N3: 343216.31
A4: Location 1 | B4: Position C | C4: 0 | D4: 0 | E4: 0 | F4: 0 | G4: 0 | H4: 0 | I4: 0 | J4: 0 | K4: 0 | L4: 0 | M4: 0 | N4: 0
A5: Location 1 | B5: Position D | C5: 15.745291 | D5: 15.745291 | E5: 17.106021 | F5: 17.38 | G5: 51777.991 | H5: 51777.991 | I5: 55730.414 | J5: 58083.13 | K5: 7300.2504 | L5: 7300.2504 | M5: 7255.5678 | N5: 8154.34
A6: Location 1 | B6: Position E | C6: 48.037148 | D6: 49.401535 | E6: 72.49387 | F6: 63.51 | G6: 94082.052 | H6: 162455.69 | I6: 203710.48 | J6: 176456.01 | K6: 22904.852 | L6: 22904.852 | M6: 44574.03 | N6: 38786.2
A7: Location 1 | B7: Position F | C7: 21.6 | D7: 24.211786 | E7: 25.5 | F7: 15.65 | G7: 76678.618 | H7: 79619.845 | I7: 84150.916 | J7: 37219.6 | K7: 11225.712 | L7: 11225.712 | M7: 23543.264 | N7: 18220
A8: Location 1 | B8: Position G | C8: 13.998619 | D8: 13.998619 | E8: 14.5 | F8: 16.11 | G8: 46034.105 | H8: 46034.105 | I8: 46759.045 | J8: 47619.3 | K8: 6490.412 | L8: 6490.412 | M8: 6170.363 | N8: 6509.13
A9: Location 1 | B9: Position H | C9: 190.79341 | D9: 185.42668 | E9: 180.01858 | F9: 168.89 | G9: 625673.71 | H9: 609770.93 | I9: 563240.4 | J9: 516731.03 | K9: 85972.445 | L9: 85972.445 | M9: 121191.63 | N9: 112868.14
A10: Location 1 | B10: Position I | C10: 88 | D10: 88 | E10: 85.75 | F10: 84.77 | G10: 289783.9 | H10: 289783.9 | I10: 294434.76 | J10: 282706 | K10: 44408.551 | L10: 44408.551 | M10: 49122.415 | N10: 51077.6
A11: Location 1 | B11: Position J | C11: 0 | D11: 0 | E11: 1 | F11: 1.35 | G11: 0 | H11: 0 | I11: 3443.0593 | J11: 3298.13 | K11: 0 | L11: 0 | M11: 203.00513 | N11: 194.46
A12: Location 1 | B12: Position K | C12: 207.91 | D12: 207.91 | E12: 224.5 | F12: 210.29 | G12: 568315.34 | H12: 568315.34 | I12: 664572.16 | J12: 586412.14 | K12: 85888.899 | L12: 85888.899 | M12: 83252.236 | N12: 71978.55
A13: Location 1 | B13: Position L | C13: 209.58129 | D13: 209.75587 | E13: 242 | F13: 214.97 | G13: 573360.98 | H13: 573360.98 | I13: 616633.57 | J13: 531760.52 | K13: 86651.44 | L13: 86651.44 | M13: 139896.64 | N13: 158726.93
... A105: Location 4 | B105: Position Z | C105: 0 | D105: 0 | E105: 0 | F105: 0 | G105: 0 | H105: 0 | I105: 0 | J105: 0 | K105: 0 | L105: 0 | M105: 0 | N105: 0
A107: Source: Workforce_Analysis.xlsx, "Workforce Data" tab, rows 5-111 (as provided by user).

Sheet Raw - Transactions
A1: Location | B1: Rental Transactions 2026 Actual (YTD) | C1: Rental Transactions 2026 Prior Forecast | D1: Rental Transactions 2026 Plan | E1: Rental Transactions 2025 Actual
A2: Location 1 | B2: 366934 | C2: 425982.47 | D2: 425982.47 | E2: 402999
A3: Location 2 | B3: 550595 | C3: 599083.3 | D3: 599083.3 | E3: 593382
A4: Location 3 | B4: 539902 | C4: 625480.95 | D4: 625480.95 | E4: 602273
A5: Location 4 | B5: 566690 | C5: 629076.38 | D5: 629076.38 | E5: 606371
