Workbook

Sheet Assumptions
A2: My Approach
A9: Assumption | B9: Rationale
A10: Bottom 5% of rental volume removed ( Final Sample =263 Locations) | B10: Reduce noise from very small locations
A11: Focused on Product 4 | B11: Largest median attachment gap
A12: +5 pp and +10 pp scenarios | B12: Conservative improvement below benchmark
A13: Scenario analysis | B13: Illustrative, not predictive

Sheet Opportunity Ranking
A2: Outputs were generated using R
A3: Similar tables were constructed for all 5 penetrations for high and low percentages
A4: Top/Bottom 10 rankings shown for Product 4.
A5: Recurring Location Frequency summarizes appearances across all five ancillary products
A7: Product 4 (Low Penetration) | I7: Recurring Locations Across All Products
A9: Rank | B9: Checkout Loc. | C9: Product 4 Pentration | D9: Walkup/No Reservation % | E9: Counter Bypass % | I9: Location | J9: # of Appearences
A10: 1 | B10: Location 23 | C10: 0 | D10: 0.0324 | E10: 0.458 | I10: 260 | J10: 3
A11: 2 | B11: Location 25 | C11: 0 | D11: 0.0231 | E11: 0.54 | I11: 137 | J11: 2
A12: 3 | B12: Location 28 | C12: 0 | D12: 0.0247 | E12: 0.432 | I12: 224 | J12: 2
A13: 4 | B13: Location 79 | C13: 0 | D13: 0.0564 | E13: 0.449 | I13: 232 | J13: 2
A14: 5 | B14: Location 21 | C14: 0.0001 | D14: 0.0425 | E14: 0.485 | I14: 248 | J14: 2
A15: 6 | B15: Location 75 | C15: 0.0001 | D15: 0.0555 | E15: 0.552 | I15: 254 | J15: 2
A16: 7 | B16: Location 100 | C16: 0.0001 | D16: 0.0265 | E16: 0.539 | I16: 263 | J16: 2
A17: 8 | B17: Location 117 | C17: 0.0001 | D17: 0.0329 | E17: 0.375 | I17: 100 | J17: 1
A18: 9 | B18: Location 47 | C18: 0.0002 | D18: 0.0324 | E18: 0.443 | I18: 105 | J18: 1
A19: 10 | B19: Location 91 | C19: 0.0002 | D19: 0.0388 | E19: 0.438 | I19: 117 | J19: 1
A21: Product 4 (HIgh Penetration)
A23: Rank | B23: Checkout Loc. | C23: Product 4 Pentration | D23: Walkup/No Reservation % | E23: Counter Bypass % | I23: Location | J23: # of Appearences
A24: 1 | B24: Location 41 | C24: 0.194 | D24: 0.0349 | E24: 0.44 | I24: 7 | J24: 4
A25: 2 | B25: Location 89 | C25: 0.217 | D25: 0.0433 | E25: 0.261 | I25: 2 | J25: 3
A26: 3 | B26: Location 6 | C26: 0.218 | D26: 0.0214 | E26: 0.509 | I26: 233 | J26: 3
A27: 4 | B27: Location 11 | C27: 0.246 | D27: 0.0466 | E27: 0.395 | I27: 8 | J27: 3
A28: 5 | B28: Location 10 | C28: 0.253 | D28: 0.0148 | E28: 0.482 | I28: 1 | J28: 2
A29: 6 | B29: Location 8 | C29: 0.26 | D29: 0.023 | E29: 0.525 | I29: 157 | J29: 2
A30: 7 | B30: Location 5 | C30: 0.281 | D30: 0.0442 | E30: 0.52 | I30: 16 | J30: 2
A31: 8 | B31: Location 16 | C31: 0.294 | D31: 0.043 | E31: 0.468 | I31: 192 | J31: 2
A32: 9 | B32: Location 1 | C32: 0.43 | D32: 0.0517 | E32: 0.395 | I32: 248 | J32: 2
A33: 10 | B33: Location 7 | C33: 0.598 | D33: 0.0375 | E33: 0.305 | I33: 251 | J33: 2

Sheet Benchmark Comparison
A2: Key Differences Between High and Low Performing Locations
A5: Low Performer | B5: P1 | C5: P2 | D5: P3 | E5: P4 | F5: P5
A6: Location 260 | B6: =_xlfn.XLOOKUP(A6,'RAW DATA'!A:A,'RAW DATA'!T:T) -> 0.0249 | C6: =_xlfn.XLOOKUP(A6,'RAW DATA'!A:A,'RAW DATA'!W:W) -> 0.0084 | D6: =_xlfn.XLOOKUP(A6,'RAW DATA'!A:A,'RAW DATA'!Z:Z) -> 0.0132 | E6: =_xlfn.XLOOKUP(A6,'RAW DATA'!A:A,'RAW DATA'!AC:AC) -> 0.005 | F6: =_xlfn.XLOOKUP(A6,'RAW DATA'!A:A,'RAW DATA'!AF:AF) -> 0.0031
A7: Location 137 | B7: =_xlfn.XLOOKUP(A7,'RAW DATA'!A:A,'RAW DATA'!T:T) -> 0.0505 | C7: =_xlfn.XLOOKUP(A7,'RAW DATA'!A:A,'RAW DATA'!W:W) -> 0.0143 | D7: =_xlfn.XLOOKUP(A7,'RAW DATA'!A:A,'RAW DATA'!Z:Z) -> 0.0222 | E7: =_xlfn.XLOOKUP(A7,'RAW DATA'!A:A,'RAW DATA'!AC:AC) -> 0.0004 | F7: =_xlfn.XLOOKUP(A7,'RAW DATA'!A:A,'RAW DATA'!AF:AF) -> 0.0131
A8: Location 224 | B8: =_xlfn.XLOOKUP(A8,'RAW DATA'!A:A,'RAW DATA'!T:T) -> 0.0509 | C8: =_xlfn.XLOOKUP(A8,'RAW DATA'!A:A,'RAW DATA'!W:W) -> 0.0192 | D8: =_xlfn.XLOOKUP(A8,'RAW DATA'!A:A,'RAW DATA'!Z:Z) -> 0.0153 | E8: =_xlfn.XLOOKUP(A8,'RAW DATA'!A:A,'RAW DATA'!AC:AC) -> 0.011 | F8: =_xlfn.XLOOKUP(A8,'RAW DATA'!A:A,'RAW DATA'!AF:AF) -> 0.003
A10: High Performers | B10: P1 | C10: P2 | D10: P3 | E10: P4 | F10: P5
A11: Location 7 | B11: =_xlfn.XLOOKUP(A11,'RAW DATA'!A:A,'RAW DATA'!T:T) -> 0.0727 | C11: =_xlfn.XLOOKUP(A11,'RAW DATA'!A:A,'RAW DATA'!W:W) -> 0.0969 | D11: =_xlfn.XLOOKUP(A11,'RAW DATA'!A:A,'RAW DATA'!Z:Z) -> 0.1905 | E11: =_xlfn.XLOOKUP(A11,'RAW DATA'!A:A,'RAW DATA'!AC:AC) -> 0.598 | F11: =_xlfn.XLOOKUP(A11,'RAW DATA'!A:A,'RAW DATA'!AF:AF) -> 0.2699
A12: Location 157 | B12: =_xlfn.XLOOKUP(A12,'RAW DATA'!A:A,'RAW DATA'!T:T) -> 0.1277 | C12: =_xlfn.XLOOKUP(A12,'RAW DATA'!A:A,'RAW DATA'!W:W) -> 0.3092 | D12: =_xlfn.XLOOKUP(A12,'RAW DATA'!A:A,'RAW DATA'!Z:Z) -> 0.2306 | E12: =_xlfn.XLOOKUP(A12,'RAW DATA'!A:A,'RAW DATA'!AC:AC) -> 0.0392 | F12: =_xlfn.XLOOKUP(A12,'RAW DATA'!A:A,'RAW DATA'!AF:AF) -> 0.0107
A13: Location 233 | B13: =_xlfn.XLOOKUP(A13,'RAW DATA'!A:A,'RAW DATA'!T:T) -> 0.2646 | C13: =_xlfn.XLOOKUP(A13,'RAW DATA'!A:A,'RAW DATA'!W:W) -> 0.0979 | D13: =_xlfn.XLOOKUP(A13,'RAW DATA'!A:A,'RAW DATA'!Z:Z) -> 0.1575 | E13: =_xlfn.XLOOKUP(A13,'RAW DATA'!A:A,'RAW DATA'!AC:AC) -> 0.1544 | F13: =_xlfn.XLOOKUP(A13,'RAW DATA'!A:A,'RAW DATA'!AF:AF) -> 0.0179
A16: High- Low Performers | C16: Median Prodcut Gap (percentage points) | D16: 0.1752 | E16: 0.1494
C17: Mean Product Gap (percentage points) | D17: 0.17596667 | E17: 0.2584
A21: Checkout Loc. | B21: Number of Rentals | C21: % of Avis Transactions | D21: Commercial Transactions | E21: Leisure Transactions | F21: % CORE | G21: % EV | H21: % PICKUP | I21: % SPECIALTY | J21: % SUV | K21: % VAN | L21: Counter Bypass % | M21: Walkup/No Reservation %
A22: Location 260 | B22: 3342 | C22: 1 | D22: 2839 | E22: 503 | F22: 0.8537 | G22: 0 | H22: 0.0003 | I22: 0.0009 | J22: 0.102 | K22: 0.0431 | L22: 0.8121 | M22: 0.0081
A23: Location 137 | B23: 22905 | C23: 0.4099 | D23: 10484 | E23: 12421 | F23: 0.7916 | G23: 0.0074 | H23: 0.0141 | I23: 0.0436 | J23: 0.104 | K23: 0.0393 | L23: 0.3272 | M23: 0.0406
A24: Location 224 | B24: 5653 | C24: 0.5946 | D24: 2119 | E24: 3534 | F24: 0.7674 | G24: 0.0177 | H24: 0.0018 | I24: 0.0513 | J24: 0.13 | K24: 0.0318 | L24: 0.3333 | M24: 0.0368
A26: Location 7 | B26: 392991 | C26: 0.5754 | D26: 72162 | E26: 320829 | F26: 0.6107 | G26: 0.0216 | H26: 0.0055 | I26: 0.0618 | J26: 0.2217 | K26: 0.0787 | L26: 0.3054 | M26: 0.0375
A27: Location 157 | B27: 15145 | C27: 1 | D27: 998 | E27: 14147 | F27: 0.6632 | G27: 0.0085 | H27: 0.0039 | I27: 0.0153 | J27: 0.1794 | K27: 0.1297 | L27: 0.1076 | M27: 0.0929
A28: Location 233 | B28: 4900 | C28: 0.6069 | D28: 777 | E28: 4123 | F28: 0.6839 | G28: 0.0016 | H28: 0.0045 | I28: 0.0649 | J28: 0.1751 | K28: 0.07 | L28: 0.2598 | M28: 0.0792

Sheet Revenue Scenario
A8: Checkout Loc. | B8: Number of Rentals | C8: Length of Rental (in Days) | D8: Product 4 Revenue | E8: Product 4 Penetration | F8: Product 4 Rate per Sold Day | G8: My Product 4 Revenue
A9: Location 260 | B9: 3342 | C9: 4.41 | D9: 1037 | E9: 0.005 | F9: 13.95 | G9: =F9*E9*C9*B9 -> 1027.9908
A14: Checkout Loc. | B14: Scenario | C14: P4 Penetration | D14: Actual Revenue | E14: Projected Revenue | F14: Incremental Revenue
A15: 260 | B15: Current | C15: 0.005 | D15: 1037 | E15: 1037 | F15: —
A16: 260 | B16: 5 pp (conservative) | C16: 5.50% | D16: 1037 | E16: =C9*C16*F9*B9 -> 11307.899 | F16: =E16-E15 -> 10270.899
A17: 260 | B17: 10 pp (moderate) | C17: 10.50% | D17: 1037 | E17: =B9*C17*F9*C9 -> 21587.808 | F17: =E17-E15 -> 20550.808

Sheet RAW DATA
C1: Brand | F1: Origin | H1: Customer Segment | J1: Car Type | S1: Counter Sales/Ancillary Sales Data
A2: Checkout Location Code | B2: Number of Rentals | C2: % of Avis Transactions | D2: % of Budget Transactions | E2: % of Payless Transactions | F2: Domestic Transactions | G2: Inbound Transactions | H2: Commercial Transactions | I2: Leisure Transactions | J2: % CORE | K2: % EV | L2: % PICKUP | M2: % SPECIALTY | N2: % SUV | O2: % VAN | P2: Counter Bypass % | Q2: Walkup/No Reservation % | R2: Length of Rental (in Days) | S2: Product 1 Revenue | T2: Product 1 Penetration | U2: Product 1 Rate per Sold Day | V2: Product 2 Revenue | W2: Product 2 Penetration | X2: Product 2 Rate per Sold Day | Y2: Product 3 Revenue | Z2: Product 3 Penetration | AA2: Product 3 Rate per Sold Day | AB2: Product 4 Revenue | AC2: Product 4 Penetration | AD2: Product 4 Rate per Sold Day | AE2: Product 5 Revenue | AF2: Product 5 Penetration | AG2: Product 5 Rate per Sold Day
A3: Location 1 | B3: 800283 | C3: 0.5163 | D3: 0.4705 | E3: 0.0132 | F3: 663273 | G3: 137010 | H3: 200909 | I3: 599374 | J3: 0.6092 | K3: 0.0269 | L3: 0.0085 | M3: 0.0433 | N3: 0.2085 | O3: 0.1036 | P3: 0.3953 | Q3: 0.0517 | R3: 4.98 | S3: 16015071 | T3: 0.0957 | U3: 41.98 | V3: 5575719 | W3: 0.0754 | X3: 18.55 | Y3: 2328861 | Z3: 0.0676 | AA3: 8.64 | AB3: 21038826 | AC3: 0.4301 | AD3: 12.27 | AE3: 8340933 | AF3: 0.232 | AG3: 9.02
A4: Location 2 | B4: 594242 | C4: 0.6158 | D4: 0.3517 | E4: 0.0325 | F4: 488545 | G4: 105697 | H4: 201263 | I4: 392979 | J4: 0.6727 | K4: 0.0519 | L4: 0.0134 | M4: 0.069 | N4: 0.1491 | O4: 0.044 | P4: 0.4451 | Q4: 0.0145 | R4: 4.47 | S4: 10220696 | T4: 0.1155 | U4: 33.31 | V4: 5722793 | W4: 0.1311 | X4: 16.43 | Y4: 4198254 | Z4: 0.1807 | AA4: 8.75 | AB4: 3697070 | AC4: 0.1201 | AD4: 11.59 | AE4: 5737212 | AF4: 0.1584 | AG4: 13.63
A5: Location 3 | B5: 571216 | C5: 0.5507 | D5: 0.4149 | E5: 0.0345 | F5: 552698 | G5: 18518 | H5: 205657 | I5: 365559 | J5: 0.6 | K5: 0.0309 | L5: 0.0294 | M5: 0.0547 | N5: 0.2537 | O5: 0.0313 | P5: 0.4942 | Q5: 0.0168 | R5: 3.83 | S5: 9391543 | T5: 0.0988 | U5: 43.51 | V5: 2408080 | W5: 0.0501 | X5: 21.98 | Y5: 1144434 | Z5: 0.0575 | AA5: 9.11 | AB5: 4364174 | AC5: 0.163 | AD5: 12.25 | AE5: 4144535 | AF5: 0.1534 | AG5: 12.37
A6: Location 4 | B6: 528774 | C6: 0.5379 | D6: 0.3902 | E6: 0.0719 | F6: 508432 | G6: 20342 | H6: 185830 | I6: 342944 | J6: 0.6178 | K6: 0.0504 | L6: 0.0124 | M6: 0.0724 | N6: 0.2045 | O6: 0.0424 | P6: 0.4603 | Q6: 0.0249 | R6: 4.07 | S6: 9658629 | T6: 0.1084 | U6: 41.41 | V6: 1907658 | W6: 0.0424 | X6: 20.89 | Y6: 799586 | Z6: 0.0412 | AA6: 9.02 | AB6: 65509 | AC6: 0.0024 | AD6: 12.75 | AE6: 3104480 | AF6: 0.1183 | AG6: 12.19
A7: Location 5 | B7: 450581 | C7: 0.6584 | D7: 0.3139 | E7: 0.0277 | F7: 424505 | G7: 26076 | H7: 208817 | I7: 241764 | J7: 0.7036 | K7: 0.03 | L7: 0.0228 | M7: 0.061 | N7: 0.1471 | O7: 0.0356 | P7: 0.5198 | Q7: 0.0442 | R7: 3.51 | S7: 6341246 | T7: 0.0942 | U7: 42.57 | V7: 2642410 | W7: 0.0803 | X7: 20.81 | Y7: 1048603 | Z7: 0.0714 | AA7: 9.3 | AB7: 6077627 | AC7: 0.2808 | AD7: 13.69 | AE7: 2434746 | AF7: 0.1264 | AG7: 12.18
A8: Location 6 | B8: 410451 | C8: 0.6447 | D8: 0.3553 | E8: 0 | F8: 344086 | G8: 66365 | H8: 171508 | I8: 238943 | J8: 0.7009 | K8: 0.0457 | L8: 0.0156 | M8: 0.0592 | N8: 0.1407 | O8: 0.0379 | P8: 0.5088 | Q8: 0.0214 | R8: 4.59 | S8: 4617389 | T8: 0.0739 | U8: 33.2 | V8: 1995409 | W8: 0.0643 | X8: 16.47 | Y8: 864763 | Z8: 0.0531 | AA8: 8.64 | AB8: 5035438 | AC8: 0.2182 | AD8: 12.26 | AE8: 3047498 | AF8: 0.1013 | AG8: 15.98
A9: Location 7 | B9: 392991 | C9: 0.5754 | D9: 0.4185 | E9: 0.0061 | F9: 232191 | G9: 160800 | H9: 72162 | I9: 320829 | J9: 0.6107 | K9: 0.0216 | L9: 0.0055 | M9: 0.0618 | N9: 0.2217 | O9: 0.0787 | P9: 0.3054 | Q9: 0.0375 | R9: 5.19 | S9: 6164283 | T9: 0.0727 | U9: 41.56 | V9: 3728640 | W9: 0.0969 | X9: 18.86 | Y9: 3360430 | Z9: 0.1905 | AA9: 8.64 | AB9: 14554029 | AC9: 0.598 | AD9: 11.93 | AE9: 4161703 | AF9: 0.2699 | AG9: 7.56
A10: Location 8 | B10: 378538 | C10: 0.6321 | D10: 0.3463 | E10: 0.0216 | F10: 346824 | G10: 31714 | H10: 157606 | I10: 220932 | J10: 0.6822 | K10: 0.0286 | L10: 0.0135 | M10: 0.0649 | N10: 0.1681 | O10: 0.0427 | P10: 0.5252 | Q10: 0.023 | R10: 3.47 | S10: 4811379 | T10: 0.0877 | U10: 41.78 | V10: 1308448 | W10: 0.051 | X10: 19.55 | Y10: 1245995 | Z10: 0.1016 | AA10: 9.34 | AB10: 4177359 | AC10: 0.2603 | AD10: 12.23 | AE10: 3797907 | AF10: 0.1965 | AG10: 14.72
A11: Location 9 | B11: 371306 | C11: 0.5856 | D11: 0.3752 | E11: 0.0391 | F11: 354225 | G11: 17081 | H11: 156987 | I11: 214319 | J11: 0.6949 | K11: 0.0406 | L11: 0.0274 | M11: 0.0563 | N11: 0.1286 | O11: 0.0522 | P11: 0.461 | Q11: 0.0275 | R11: 4.5 | S11: 6647499 | T11: 0.1029 | U11: 38.67 | V11: 2390154 | W11: 0.091 | X11: 15.72 | Y11: 764385 | Z11: 0.0515 | AA11: 8.89 | AB11: 1526231 | AC11: 0.0804 | AD11: 11.36 | AE11: 2174223 | AF11: 0.0789 | AG11: 16.49
A12: Location 10 | B12: 368051 | C12: 0.5792 | D12: 0.4078 | E12: 0.013 | F12: 334981 | G12: 33070 | H12: 132733 | I12: 235318 | J12: 0.6929 | K12: 0.0145 | L12: 0.0149 | M12: 0.0533 | N12: 0.182 | O12: 0.0425 | P12: 0.4823 | Q12: 0.0148 | R12: 4.3 | S12: 6626531 | T12: 0.1119 | U12: 37.41 | V12: 2062361 | W12: 0.0677 | X12: 19.25 | Y12: 1215292 | Z12: 0.0849 | AA12: 9.05 | AB12: 5849853 | AC12: 0.2534 | AD12: 14.59 | AE12: 2597552 | AF12: 0.1242 | AG12: 13.22
A13: Location 11 | B13: 357616 | C13: 0.4969 | D13: 0.4955 | E13: 0.0076 | F13: 304350 | G13: 53266 | H13: 81952 | I13: 275664 | J13: 0.6027 | K13: 0.0255 | L13: 0.0076 | M13: 0.061 | N13: 0.226 | O13: 0.0772 | P13: 0.3952 | Q13: 0.0466 | R13: 4.48 | S13: 4980069 | T13: 0.0758 | U13: 40.96 | V13: 2445987 | W13: 0.0805 | X13: 18.94 | Y13: 342489 | Z13: 0.0239 | AA13: 8.95 | AB13: 5016547 | AC13: 0.2456 | AD13: 12.74 | AE13: 1795200 | AF13: 0.1181 | AG13: 9.48
A14: Location 12 | B14: 355996 | C14: 0.5079 | D14: 0.4795 | E14: 0.0127 | F14: 329927 | G14: 26069 | H14: 95783 | I14: 260213 | J14: 0.6312 | K14: 0.0274 | L14: 0.0112 | M14: 0.0464 | N14: 0.2194 | O14: 0.0642 | P14: 0.4361 | Q14: 0.0231 | R14: 4.73 | S14: 6794008 | T14: 0.0951 | U14: 42.43 | V14: 2424339 | W14: 0.0773 | X14: 18.63 | Y14: 506332 | Z14: 0.0341 | AA14: 8.82 | AB14: 3442174 | AC14: 0.1628 | AD14: 12.56 | AE14: 2828629 | AF14: 0.1805 | AG14: 9.31
... A21: Location 19 | B21: 259981 | C21: 0.5569 | D21: 0.4431 | E21: 0 | F21: 247812 | G21: 12169 | H21: 98322 | I21: 161659 | J21: 0.7137 | K21: 0.0176 | L21: 0.0287 | M21: 0.0512 | N21: 0.1524 | O21: 0.0364 | P21: 0.4846 | Q21: 0.0253 | R21: 3.7 | S21: 3330523 | T21: 0.0923 | U21: 37.52 | V21: 1088710 | W21: 0.053 | X21: 21.36 | Y21: 274868 | Z21: 0.0307 | AA21: 9.31 | AB21: 237110 | AC21: 0.0209 | AD21: 11.8 | AE21: 1076311 | AF21: 0.0879 | AG21: 12.73
A22: Location 20 | B22: 256962 | C22: 0.3919 | D22: 0.5732 | E22: 0.0349 | F22: 237915 | G22: 19047 | H22: 65928 | I22: 191034 | J22: 0.5884 | K22: 0.029 | L22: 0.1004 | M22: 0.0828 | N22: 0.1164 | O22: 0.0829 | P22: 0.3547 | Q22: 0.0326 | R22: 5.11 | S22: 7573626 | T22: 0.1734 | U22: 33.26 | V22: 1300842 | W22: 0.0639 | X22: 15.5 | Y22: 589900 | Z22: 0.0501 | AA22: 8.97 | AB22: 0 | AE22: 1169195 | AF22: 0.0653 | AG22: 13.62
A23: Location 21 | B23: 255668 | C23: 0.9142 | D23: 0 | E23: 0.0858 | F23: 224370 | G23: 31298 | H23: 91743 | I23: 163925 | J23: 0.6186 | K23: 0.0436 | L23: 0.0224 | M23: 0.0821 | N23: 0.1792 | O23: 0.054 | P23: 0.4854 | Q23: 0.0425 | R23: 4.13 | S23: 4726374 | T23: 0.1315 | U23: 34.01 | V23: 1429805 | W23: 0.0725 | X23: 18.65 | Y23: 1075564 | Z23: 0.1146 | AA23: 8.88 | AB23: 2047 | AC23: 0.0001 | AD23: 20.27 | AE23: 938128 | AF23: 0.0621 | AG23: 14.28
A24: Location 22 | B24: 239141 | C24: 0.5473 | D24: 0.418 | E24: 0.0346 | F24: 232244 | G24: 6897 | H24: 97766 | I24: 141375 | J24: 0.7221 | K24: 0.019 | L24: 0.0214 | M24: 0.0517 | N24: 0.1474 | O24: 0.0384 | P24: 0.4721 | Q24: 0.0201 | R24: 3.82 | S24: 2981528 | T24: 0.0889 | U24: 36.75 | V24: 586260 | W24: 0.0311 | X24: 20.67 | Y24: 344163 | Z24: 0.0407 | AA24: 9.27 | AB24: 70812 | AC24: 0.0065 | AD24: 11.88 | AE24: 1010778 | AF24: 0.0865 | AG24: 12.81
A25: Location 23 | B25: 238963 | C25: 0.5623 | D25: 0.4128 | E25: 0.0248 | F25: 230854 | G25: 8109 | H25: 89589 | I25: 149374 | J25: 0.6758 | K25: 0.0092 | L25: 0.018 | M25: 0.05 | N25: 0.1903 | O25: 0.0568 | P25: 0.4584 | Q25: 0.0324 | R25: 3.49 | S25: 3096096 | T25: 0.0969 | U25: 38.33 | V25: 935219 | W25: 0.0526 | X25: 21.35 | Y25: 334619 | Z25: 0.043 | AA25: 9.34 | AB25: 486 | AC25: 0 | AD25: 15.56 | AE25: 1457315 | AF25: 0.1532 | AG25: 11.42
A26: Location 24 | B26: 229536 | C26: 0.3898 | D26: 0.5465 | E26: 0.0637 | F26: 211903 | G26: 17633 | H26: 47809 | I26: 181727 | J26: 0.5476 | K26: 0.04 | L26: 0.1161 | M26: 0.0639 | N26: 0.1505 | O26: 0.0819 | P26: 0.351 | Q26: 0.0181 | R26: 5.99 | S26: 4275795 | T26: 0.095 | U26: 32.74 | V26: 926378 | W26: 0.0445 | X26: 15.13 | Y26: 718532 | Z26: 0.0591 | AA26: 8.84 | AB26: 0 | AE26: 982057 | AF26: 0.0603 | AG26: 11.84
A27: Location 25 | B27: 223371 | C27: 0.9401 | D27: 0 | E27: 0.0599 | F27: 215711 | G27: 7660 | H27: 106336 | I27: 117035 | J27: 0.7077 | K27: 0.0078 | L27: 0.0253 | M27: 0.0604 | N27: 0.1691 | O27: 0.0296 | P27: 0.5404 | Q27: 0.0231 | R27: 3.85 | S27: 2580355 | T27: 0.0839 | U27: 35.71 | V27: 797272 | W27: 0.0446 | X27: 20.74 | Y27: 322455 | Z27: 0.0415 | AA27: 9.02 | AB27: 336 | AC27: 0 | AD27: 22.43 | AE27: 901122 | AF27: 0.0786 | AG27: 13.31
A28: Location 26 | B28: 218165 | C28: 0.4138 | D28: 0.5704 | E28: 0.0158 | F28: 209793 | G28: 8372 | H28: 39705 | I28: 178460 | J28: 0.6085 | K28: 0.0089 | L28: 0.0097 | M28: 0.0545 | N28: 0.24 | O28: 0.0784 | P28: 0.4128 | Q28: 0.0168 | R28: 5.9 | S28: 3188149 | T28: 0.0644 | U28: 38.47 | V28: 749011 | W28: 0.0314 | X28: 18.56 | Y28: 165437 | Z28: 0.0148 | AA28: 8.7 | AB28: 915922 | AC28: 0.0598 | AD28: 11.91 | AE28: 1662535 | AF28: 0.1597 | AG28: 8.09
A29: Location 27 | B29: 201208 | C29: 0.5589 | D29: 0.4192 | E29: 0.022 | F29: 164086 | G29: 37122 | H29: 35380 | I29: 165828 | J29: 0.62 | K29: 0.0153 | L29: 0.0307 | M29: 0.0655 | N29: 0.1968 | O29: 0.0718 | P29: 0.33 | Q29: 0.0433 | R29: 4.63 | S29: 3182103 | T29: 0.2 | U29: 17.09 | V29: 1794937 | W29: 0.098 | X29: 19.67 | Y29: 466802 | Z29: 0.0558 | AA29: 8.98 | AB29: 3913312 | AC29: 0.1672 | AD29: 25.13 | AE29: 791004 | AF29: 0.062 | AG29: 13.71
A30: Location 28 | B30: 201177 | C30: 0.5549 | D30: 0.3975 | E30: 0.0476 | F30: 197659 | G30: 3518 | H30: 66594 | I30: 134583 | J30: 0.7018 | K30: 0.0288 | L30: 0.0144 | M30: 0.0764 | N30: 0.136 | O30: 0.0426 | P30: 0.432 | Q30: 0.0247 | R30: 4.28 | S30: 2762474 | T30: 0.0858 | U30: 37.37 | V30: 666467 | W30: 0.0409 | X30: 18.91 | Y30: 247697 | Z30: 0.0321 | AA30: 8.97 | AB30: 48 | AC30: 0 | AD30: 23.84 | AE30: 981515 | AF30: 0.0812 | AG30: 14.04
A31: Location 29 | B31: 200435 | C31: 0.6317 | D31: 0.3437 | E31: 0.0246 | F31: 192777 | G31: 7658 | H31: 84875 | I31: 115560 | J31: 0.686 | K31: 0.0416 | L31: 0.0158 | M31: 0.0517 | N31: 0.1616 | O31: 0.0432 | P31: 0.4914 | Q31: 0.0281 | R31: 3.76 | S31: 2595115 | T31: 0.0872 | U31: 39.47 | V31: 835379 | W31: 0.0542 | X31: 20.43 | Y31: 346295 | Z31: 0.0505 | AA31: 9.1 | AB31: 1922062 | AC31: 0.192 | AD31: 13.27 | AE31: 864875 | AF31: 0.1068 | AG31: 10.73
A32: Location 30 | B32: 200208 | C32: 0.5402 | D32: 0.4435 | E32: 0.0163 | F32: 194806 | G32: 5402 | H32: 70412 | I32: 129796 | J32: 0.7257 | K32: 0.0164 | L32: 0.0307 | M32: 0.0487 | N32: 0.1311 | O32: 0.0474 | P32: 0.4564 | Q32: 0.0152 | R32: 3.71 | S32: 2278934 | T32: 0.0805 | U32: 38.1 | V32: 780746 | W32: 0.0494 | X32: 21.27 | Y32: 170357 | Z32: 0.0249 | AA32: 9.2 | AB32: 294798 | AC32: 0.033 | AD32: 12 | AE32: 981947 | AF32: 0.1016 | AG32: 13
A33: Location 31 | B33: 192178 | C33: 0.6188 | D33: 0.3812 | E33: 0 | F33: 177519 | G33: 14659 | H33: 79874 | I33: 112304 | J33: 0.7035 | K33: 0.0195 | L33: 0.0291 | M33: 0.041 | N33: 0.1592 | O33: 0.0477 | P33: 0.4842 | Q33: 0.052 | R33: 4.21 | S33: 3450407 | T33: 0.1157 | U33: 36.85 | V33: 1198144 | W33: 0.0816 | X33: 18.15 | Y33: 584130 | Z33: 0.0824 | AA33: 8.76 | AB33: 1969404 | AC33: 0.099 | AD33: 24.59 | AE33: 632461 | AF33: 0.0654 | AG33: 11.95
A34: Location 32 | B34: 191061 | C34: 0.4619 | D34: 0.4975 | E34: 0.0407 | F34: 188327 | G34: 2734 | H34: 58896 | I34: 132165 | J34: 0.6483 | K34: 0.0732 | L34: 0.0245 | M34: 0.0795 | N34: 0.1369 | O34: 0.0375 | P34: 0.4117 | Q34: 0.029 | R34: 4.02 | S34: 3980842 | T34: 0.1511 | U34: 34.32 | V34: 672693 | W34: 0.0524 | X34: 16.74 | Y34: 226033 | Z34: 0.0315 | AA34: 9.34 | AB34: 104821 | AC34: 0.0096 | AD34: 14.2 | AE34: 904708 | AF34: 0.058 | AG34: 20.32
A35: Location 33 | B35: 188522 | C35: 0.5432 | D35: 0.4315 | E35: 0.0253 | F35: 181220 | G35: 7302 | H35: 46934 | I35: 141588 | J35: 0.6377 | K35: 0.0208 | L35: 0.03 | M35: 0.0562 | N35: 0.1804 | O35: 0.075 | P35: 0.4038 | Q35: 0.0273 | R35: 3.52 | S35: 2163651 | T35: 0.18 | U35: 18.11 | V35: 956223 | W35: 0.0716 | X35: 20.13 | Y35: 315707 | Z35: 0.0508 | AA35: 9.36 | AB35: 1994689 | AC35: 0.1096 | AD35: 27.42 | AE35: 501235 | AF35: 0.0488 | AG35: 15.49
A36: Location 34 | B36: 186005 | C36: 0.684 | D36: 0.2833 | E36: 0.0327 | F36: 182456 | G36: 3549 | H36: 101457 | I36: 84548 | J36: 0.7448 | K36: 0.04 | L36: 0.0208 | M36: 0.0432 | N36: 0.1123 | O36: 0.0391 | P36: 0.5909 | Q36: 0.016 | R36: 3.76 | S36: 1761476 | T36: 0.0782 | U36: 32.22 | V36: 824900 | W36: 0.0716 | X36: 16.48 | Y36: 198516 | Z36: 0.0309 | AA36: 9.2 | AB36: 251216 | AC36: 0.0279 | AD36: 12.9 | AE36: 415888 | AF36: 0.0321 | AG36: 18.57
A37: Location 35 | B37: 185162 | C37: 0.5614 | D37: 0.4386 | E37: 0 | F37: 183501 | G37: 1661 | H37: 68005 | I37: 117157 | J37: 0.69 | K37: 0.0173 | L37: 0.0274 | M37: 0.0517 | N37: 0.1659 | O37: 0.0477 | P37: 0.4752 | Q37: 0.0316 | R37: 3.82 | S37: 2355284 | T37: 0.0894 | U37: 37.28 | V37: 849489 | W37: 0.066 | X37: 18.23 | Y37: 489570 | Z37: 0.0713 | AA37: 9.72 | AB37: 1404859 | AC37: 0.074 | AD37: 26.86 | AE37: 749118 | AF37: 0.079 | AG37: 13.42
A38: Location 36 | B38: 179643 | C38: 0.5127 | D38: 0.4771 | E38: 0.0102 | F38: 175609 | G38: 4034 | H38: 48525 | I38: 131118 | J38: 0.6277 | K38: 0.0224 | L38: 0.0116 | M38: 0.0593 | N38: 0.2243 | O38: 0.0548 | P38: 0.4271 | Q38: 0.0339 | R38: 5.29 | S38: 2267890 | T38: 0.0644 | U38: 37.01 | V38: 661224 | W38: 0.0372 | X38: 18.69 | Y38: 136857 | Z38: 0.0165 | AA38: 8.71 | AB38: 1013241 | AC38: 0.0869 | AD38: 12.26 | AE38: 804667 | AF38: 0.092 | AG38: 9.2
... A43: Location 41 | B43: 164256 | C43: 0.456 | D43: 0.4599 | E43: 0.0841 | F43: 163482 | G43: 774 | H43: 54359 | I43: 109897 | J43: 0.6807 | K43: 0.0315 | L43: 0.0326 | M43: 0.0619 | N43: 0.1509 | O43: 0.0425 | P43: 0.4403 | Q43: 0.0349 | R43: 3.32 | S43: 2755474 | T43: 0.1164 | U43: 43.42 | V43: 800830 | W43: 0.0709 | X43: 20.72 | Y43: 373713 | Z43: 0.0705 | AA43: 9.73 | AB43: 1502475 | AC43: 0.194 | AD43: 14.21 | AE43: 793851 | AF43: 0.1129 | AG43: 12.89
A44: Location 42 | B44: 153494 | C44: 0.3741 | D44: 0.597 | E44: 0.0288 | F44: 147219 | G44: 6275 | H44: 31303 | I44: 122191 | J44: 0.6365 | K44: 0.0071 | L44: 0.0824 | M44: 0.0465 | N44: 0.1552 | O44: 0.0722 | P44: 0.328 | Q44: 0.0169 | R44: 5.59 | S44: 3847300 | T44: 0.1356 | U44: 33.04 | V44: 446731 | W44: 0.0336 | X44: 15.47 | Y44: 406812 | Z44: 0.0534 | AA44: 8.87 | AB44: 0 | AE44: 1045399 | AF44: 0.0928 | AG44: 13.12
A45: Location 43 | B45: 147826 | C45: 0.3826 | D45: 0.572 | E45: 0.0454 | F45: 135738 | G45: 12088 | H45: 29297 | I45: 118529 | J45: 0.5589 | K45: 0.0002 | L45: 0.1371 | M45: 0.0548 | N45: 0.1831 | O45: 0.0659 | P45: 0.3333 | Q45: 0.0134 | R45: 5.94 | S45: 2697290 | T45: 0.0925 | U45: 33.22 | V45: 733278 | W45: 0.0549 | X45: 15.21 | Y45: 291729 | Z45: 0.038 | AA45: 8.75 | AB45: 0 | AE45: 909684 | AF45: 0.0812 | AG45: 12.76
A46: Location 44 | B46: 147802 | C46: 0.9172 | D46: 0 | E46: 0.0828 | F46: 145036 | G46: 2766 | H46: 67341 | I46: 80461 | J46: 0.7168 | K46: 0.0307 | L46: 0.0203 | M46: 0.045 | N46: 0.1535 | O46: 0.0338 | P46: 0.5083 | Q46: 0.0336 | R46: 3.45 | S46: 2073687 | T46: 0.0943 | U46: 43.15 | V46: 665031 | W46: 0.0733 | X46: 17.8 | Y46: 425207 | Z46: 0.0874 | AA46: 9.54 | AB46: 254040 | AC46: 0.0397 | AD46: 12.55 | AE46: 654453 | AF46: 0.1064 | AG46: 12.07
A47: Location 45 | B47: 140480 | C47: 0.5774 | D47: 0.3691 | E47: 0.0535 | F47: 137724 | G47: 2756 | H47: 57753 | I47: 82727 | J47: 0.6756 | K47: 0.0202 | L47: 0.0161 | M47: 0.0612 | N47: 0.1871 | O47: 0.0398 | P47: 0.4796 | Q47: 0.0195 | R47: 3.72 | S47: 1607962 | T47: 0.0801 | U47: 38.42 | V47: 490516 | W47: 0.0515 | X47: 18.24 | Y47: 210237 | Z47: 0.0437 | AA47: 9.21 | AB47: 73817 | AC47: 0.0114 | AD47: 12.4 | AE47: 556961 | AF47: 0.0723 | AG47: 14.73
A48: Location 46 | B48: 135602 | C48: 0.5886 | D48: 0.4094 | E48: 0.0019 | F48: 132275 | G48: 3327 | H48: 48698 | I48: 86904 | J48: 0.6662 | K48: 0.0236 | L48: 0.0162 | M48: 0.0713 | N48: 0.1812 | O48: 0.0416 | P48: 0.4478 | Q48: 0.0337 | R48: 3.79 | S48: 1724942 | T48: 0.0884 | U48: 37.95 | V48: 523810 | W48: 0.0529 | X48: 19.28 | Y48: 138365 | Z48: 0.0287 | AA48: 9.37 | AB48: 101082 | AC48: 0.011 | AD48: 17.83 | AE48: 385198 | AF48: 0.0501 | AG48: 14.96
A49: Location 47 | B49: 132629 | C49: 0.5044 | D49: 0.4668 | E49: 0.0287 | F49: 127800 | G49: 4829 | H49: 47334 | I49: 85295 | J49: 0.7003 | K49: 0.012 | L49: 0.0153 | M49: 0.0573 | N49: 0.1699 | O49: 0.0451 | P49: 0.4427 | Q49: 0.0324 | R49: 3.71 | S49: 1471613 | T49: 0.0763 | U49: 39.21 | V49: 329952 | W49: 0.0327 | X49: 20.53 | Y49: 74851 | Z49: 0.017 | AA49: 8.96 | AB49: 2063 | AC49: 0.0002 | AD49: 21.65 | AE49: 430974 | AF49: 0.0713 | AG49: 12.29
A50: Location 48 | B50: 131723 | C50: 0.6338 | D50: 0.3662 | E50: 0 | F50: 127682 | G50: 4041 | H50: 58727 | I50: 72996 | J50: 0.7071 | K50: 0.0211 | L50: 0.0158 | M50: 0.0465 | N50: 0.1629 | O50: 0.0466 | P50: 0.4935 | Q50: 0.0346 | R50: 3.94 | S50: 2165300 | T50: 0.1026 | U50: 40.73 | V50: 555009 | W50: 0.0522 | X50: 20.52 | Y50: 283239 | Z50: 0.0568 | AA50: 9.61 | AB50: 1880952 | AC50: 0.1574 | AD50: 23.06 | AE50: 877535 | AF50: 0.1001 | AG50: 16.92
A51: Location 49 | B51: 131176 | C51: 0.6008 | D51: 0.3631 | E51: 0.036 | F51: 125694 | G51: 5482 | H51: 52749 | I51: 78427 | J51: 0.6673 | K51: 0.0358 | L51: 0.0206 | M51: 0.05 | N51: 0.1775 | O51: 0.0487 | P51: 0.4546 | Q51: 0.0243 | R51: 4.04 | S51: 1695073 | T51: 0.0804 | U51: 39.78 | V51: 455142 | W51: 0.0416 | X51: 20.64 | Y51: 260566 | Z51: 0.0531 | AA51: 9.25 | AB51: 143758 | AC51: 0.0203 | AD51: 13.35 | AE51: 484381 | AF51: 0.0785 | AG51: 11.64
A52: Location 50 | B52: 123079 | C52: 0.5844 | D52: 0.3906 | E52: 0.025 | F52: 121653 | G52: 1426 | H52: 48124 | I52: 74955 | J52: 0.7272 | K52: 0.0188 | L52: 0.0258 | M52: 0.0509 | N52: 0.1464 | O52: 0.0309 | P52: 0.485 | Q52: 0.0187 | R52: 3.89 | S52: 1596043 | T52: 0.0907 | U52: 36.72 | V52: 279403 | W52: 0.0303 | X52: 19.26 | Y52: 262366 | Z52: 0.0584 | AA52: 9.38 | AB52: 385072 | AC52: 0.0407 | AD52: 19.73 | AE52: 597771 | AF52: 0.0914 | AG52: 13.65
A53: Location 51 | B53: 123054 | C53: 0.4836 | D53: 0.5164 | E53: 0 | F53: 121535 | G53: 1519 | H53: 50511 | I53: 72543 | J53: 0.6907 | K53: 0.0055 | L53: 0.0308 | M53: 0.0354 | N53: 0.1941 | O53: 0.0436 | P53: 0.3654 | Q53: 0.0427 | R53: 5.05 | S53: 1680352 | T53: 0.0749 | U53: 36.11 | V53: 654933 | W53: 0.0563 | X53: 18.72 | Y53: 261951 | Z53: 0.0462 | AA53: 9.13 | AB53: 140985 | AC53: 0.0089 | AD53: 25.48 | AE53: 458447 | AF53: 0.0709 | AG53: 10.41
A54: Location 52 | B54: 121389 | C54: 0.5844 | D54: 0.4156 | E54: 0 | F54: 118673 | G54: 2716 | H54: 48710 | I54: 72679 | J54: 0.7063 | K54: 0.0137 | L54: 0.0321 | M54: 0.0462 | N54: 0.1626 | O54: 0.0391 | P54: 0.4871 | Q54: 0.031 | R54: 3.7 | S54: 1657925 | T54: 0.0945 | U54: 39.07 | V54: 398745 | W54: 0.0479 | X54: 18.52 | Y54: 146109 | Z54: 0.035 | AA54: 9.28 | AB54: 368290 | AC54: 0.0332 | AD54: 24.71 | AE54: 772556 | AF54: 0.1116 | AG54: 15.42
A55: Location 53 | B55: 117255 | C55: 0.5264 | D55: 0.4736 | E55: 0 | F55: 114792 | G55: 2463 | H55: 37833 | I55: 79422 | J55: 0.6474 | K55: 0.0152 | L55: 0.0258 | M55: 0.0846 | N55: 0.1897 | O55: 0.0372 | P55: 0.422 | Q55: 0.0234 | R55: 4.32 | S55: 1725801 | T55: 0.0899 | U55: 37.93 | V55: 351458 | W55: 0.0389 | X55: 17.85 | Y55: 160700 | Z55: 0.0344 | AA55: 9.24 | AB55: 11083 | AC55: 0.0009 | AD55: 23.65 | AE55: 479189 | AF55: 0.0919 | AG55: 10.3
A56: Location 54 | B56: 115089 | C56: 0.5081 | D56: 0.4338 | E56: 0.0581 | F56: 114308 | G56: 781 | H56: 40742 | I56: 74347 | J56: 0.7005 | K56: 0.0355 | L56: 0.0209 | M56: 0.0531 | N56: 0.1522 | O56: 0.0379 | P56: 0.4448 | Q56: 0.0342 | R56: 3.34 | S56: 2016737 | T56: 0.119 | U56: 44.05 | V56: 480853 | W56: 0.0598 | X56: 20.92 | Y56: 197644 | Z56: 0.053 | AA56: 9.69 | AB56: 762354 | AC56: 0.1419 | AD56: 13.97 | AE56: 316043 | AF56: 0.0642 | AG56: 12.79
A57: Location 55 | B57: 114257 | C57: 0.5273 | D57: 0.4098 | E57: 0.0629 | F57: 112924 | G57: 1333 | H57: 41765 | I57: 72492 | J57: 0.6911 | K57: 0.0207 | L57: 0.0328 | M57: 0.0563 | N57: 0.1691 | O57: 0.0299 | P57: 0.4183 | Q57: 0.025 | R57: 4.35 | S57: 1968975 | T57: 0.1046 | U57: 37.89 | V57: 363443 | W57: 0.0469 | X57: 15.6 | Y57: 171292 | Z57: 0.0384 | AA57: 8.97 | AB57: 0 | AE57: 548801 | AF57: 0.1056 | AG57: 10.46
A58: Location 56 | B58: 112400 | C58: 0.4788 | D58: 0.5212 | E58: 0 | F58: 111310 | G58: 1090 | H58: 31740 | I58: 80660 | J58: 0.668 | K58: 0.0269 | L58: 0.0128 | M58: 0.0545 | N58: 0.1831 | O58: 0.0547 | P58: 0.4049 | Q58: 0.0215 | R58: 3.63 | S58: 1663084 | T58: 0.1024 | U58: 39.75 | V58: 354824 | W58: 0.0434 | X58: 20.02 | Y58: 162214 | Z58: 0.0421 | AA58: 9.43 | AB58: 569932 | AC58: 0.1104 | AD58: 12.64 | AE58: 870131 | AF58: 0.1331 | AG58: 16.01
A59: Location 57 | B59: 112071 | C59: 0.6213 | D59: 0.3479 | E59: 0.0308 | F59: 108404 | G59: 3667 | H59: 50426 | I59: 61645 | J59: 0.7141 | K59: 0.0233 | L59: 0.0136 | M59: 0.0657 | N59: 0.1484 | O59: 0.035 | P59: 0.5222 | Q59: 0.0223 | R59: 3.49 | S59: 1065985 | T59: 0.0719 | U59: 37.87 | V59: 377185 | W59: 0.0483 | X59: 19.95 | Y59: 117443 | Z59: 0.0337 | AA59: 8.91 | AB59: 40616 | AC59: 0.0058 | AD59: 17.82 | AE59: 338764 | AF59: 0.0708 | AG59: 12.23
A60: Location 58 | B60: 108256 | C60: 0.4783 | D60: 0.5217 | E60: 0 | F60: 104427 | G60: 3829 | H60: 29911 | I60: 78345 | J60: 0.6559 | K60: 0.0139 | L60: 0.0226 | M60: 0.04 | N60: 0.211 | O60: 0.0565 | P60: 0.3594 | Q60: 0.0301 | R60: 4.11 | S60: 1119272 | T60: 0.1474 | U60: 17.05 | V60: 391430 | W60: 0.0441 | X60: 19.91 | Y60: 162125 | Z60: 0.0394 | AA60: 9.23 | AB60: 211923 | AC60: 0.019 | AD60: 25.06 | AE60: 312511 | AF60: 0.0507 | AG60: 13.83
A61: Location 59 | B61: 105522 | C61: 0.5529 | D61: 0.3838 | E61: 0.0633 | F61: 103822 | G61: 1700 | H61: 39306 | I61: 66216 | J61: 0.6947 | K61: 0.0359 | L61: 0.0219 | M61: 0.0567 | N61: 0.1415 | O61: 0.0492 | P61: 0.4265 | Q61: 0.0308 | R61: 4.08 | S61: 2063932 | T61: 0.1412 | U61: 33.97 | V61: 447884 | W61: 0.063 | X61: 16.52 | Y61: 164679 | Z61: 0.0417 | AA61: 9.18 | AB61: 239965 | AC61: 0.044 | AD61: 12.67 | AE61: 309162 | AF61: 0.0417 | AG61: 17.23
A62: Location 60 | B62: 104892 | C62: 0.5093 | D62: 0.4907 | E62: 0 | F62: 101705 | G62: 3187 | H62: 33379 | I62: 71513 | J62: 0.6514 | K62: 0.0027 | L62: 0.0271 | M62: 0.0834 | N62: 0.1919 | O62: 0.0436 | P62: 0.4204 | Q62: 0.0272 | R62: 4 | S62: 1372963 | T62: 0.1078 | U62: 30.35 | V62: 383381 | W62: 0.0481 | X62: 18.99 | Y62: 187175 | Z62: 0.0477 | AA62: 9.36 | AB62: 0 | AE62: 555209 | AF62: 0.0752 | AG62: 17.6
A63: Location 61 | B63: 103454 | C63: 0.5149 | D63: 0.464 | E63: 0.0211 | F63: 100574 | G63: 2880 | H63: 26893 | I63: 76561 | J63: 0.6469 | K63: 0.0105 | L63: 0.0243 | M63: 0.0751 | N63: 0.2075 | O63: 0.0357 | P63: 0.3997 | Q63: 0.0315 | R63: 4.66 | S63: 1171329 | T63: 0.0675 | U63: 35.99 | V63: 217344 | W63: 0.0266 | X63: 16.93 | Y63: 81468 | Z63: 0.0194 | AA63: 8.73 | AB63: 33474 | AC63: 0.006 | AD63: 11.65 | AE63: 374287 | AF63: 0.0842 | AG63: 9.23
A64: Location 62 | B64: 100216 | C64: 0.4924 | D64: 0.4865 | E64: 0.0211 | F64: 98942 | G64: 1274 | H64: 37874 | I64: 62342 | J64: 0.7089 | K64: 0.0165 | L64: 0.0301 | M64: 0.0335 | N64: 0.1733 | O64: 0.0378 | P64: 0.4151 | Q64: 0.0377 | R64: 4.5 | S64: 1442209 | T64: 0.0914 | U64: 34.96 | V64: 369474 | W64: 0.0433 | X64: 18.9 | Y64: 134217 | Z64: 0.0318 | AA64: 9.34 | AB64: 144562 | AC64: 0.0116 | AD64: 27.59 | AE64: 310089 | AF64: 0.0477 | AG64: 14.39
A65: Location 63 | B65: 99397 | C65: 0.5516 | D65: 0.4484 | E65: 0 | F65: 98380 | G65: 1017 | H65: 37425 | I65: 61972 | J65: 0.6993 | K65: 0.0262 | L65: 0.0187 | M65: 0.046 | N65: 0.1699 | O65: 0.04 | P65: 0.4615 | Q65: 0.0214 | R65: 4.11 | S65: 1075305 | T65: 0.0676 | U65: 38.96 | V65: 275822 | W65: 0.0329 | X65: 20.52 | Y65: 119826 | Z65: 0.0315 | AA65: 9.32 | AB65: 133461 | AC65: 0.0264 | AD65: 12.37 | AE65: 367686 | AF65: 0.0752 | AG65: 11.97
A66: Location 64 | B66: 98027 | C66: 0.5787 | D66: 0.4213 | E66: 0 | F66: 96645 | G66: 1382 | H66: 40261 | I66: 57766 | J66: 0.7182 | K66: 0.0362 | L66: 0.0289 | M66: 0.0545 | N66: 0.132 | O66: 0.0301 | P66: 0.4356 | Q66: 0.0229 | R66: 4.1 | S66: 1691325 | T66: 0.1033 | U66: 40.77 | V66: 229993 | W66: 0.0334 | X66: 17.14 | Y66: 83215 | Z66: 0.0221 | AA66: 9.36 | AB66: 299133 | AC66: 0.0596 | AD66: 12.51 | AE66: 299623 | AF66: 0.0609 | AG66: 12.24
A67: Location 65 | B67: 95662 | C67: 0.4573 | D67: 0.5427 | E67: 0 | F67: 94449 | G67: 1213 | H67: 28955 | I67: 66707 | J67: 0.6905 | K67: 0.0003 | L67: 0.0182 | M67: 0.0721 | N67: 0.1929 | O67: 0.026 | P67: 0.3628 | Q67: 0.0346 | R67: 3.63 | S67: 1258030 | T67: 0.0952 | U67: 38.08 | V67: 226427 | W67: 0.0321 | X67: 20.35 | Y67: 76446 | Z67: 0.0242 | AA67: 9.09 | AB67: 0 | AE67: 262854 | AF67: 0.0551 | AG67: 13.73
A68: Location 66 | B68: 93470 | C68: 0.4095 | D68: 0.5635 | E68: 0.027 | F68: 91710 | G68: 1760 | H68: 16690 | I68: 76780 | J68: 0.6493 | K68: 0.0075 | L68: 0.0108 | M68: 0.0466 | N68: 0.2139 | O68: 0.0719 | P68: 0.3625 | Q68: 0.0239 | R68: 5.51 | S68: 1128098 | T68: 0.0555 | U68: 39.51 | V68: 227863 | W68: 0.024 | X68: 18.43 | Y68: 45667 | Z68: 0.0104 | AA68: 8.52 | AB68: 80620 | AC68: 0.0123 | AD68: 12.69 | AE68: 539221 | AF68: 0.1316 | AG68: 7.96
A69: Location 67 | B69: 90733 | C69: 0.521 | D69: 0.479 | E69: 0 | F69: 89344 | G69: 1389 | H69: 23312 | I69: 67421 | J69: 0.592 | K69: 0 | L69: 0.0281 | M69: 0.0431 | N69: 0.2935 | O69: 0.0433 | P69: 0.344 | Q69: 0.0101 | R69: 5.21 | S69: 1760395 | T69: 0.1012 | U69: 36.81 | V69: 739228 | W69: 0.1026 | X69: 15.25 | Y69: 148401 | Z69: 0.0365 | AA69: 8.61 | AB69: 0 | AE69: 427969 | AF69: 0.0807 | AG69: 11.22
A70: Location 68 | B70: 90310 | C70: 0.5537 | D70: 0.3959 | E70: 0.0504 | F70: 89750 | G70: 560 | H70: 33687 | I70: 56623 | J70: 0.7159 | K70: 0.0499 | L70: 0.0143 | M70: 0.0596 | N70: 0.1264 | O70: 0.0339 | P70: 0.4795 | Q70: 0.0219 | R70: 3.68 | S70: 1148253 | T70: 0.1043 | U70: 33.11 | V70: 278697 | W70: 0.0502 | X70: 16.69 | Y70: 87019 | Z70: 0.0286 | AA70: 9.15 | AB70: 26139 | AC70: 0.006 | AD70: 13.02 | AE70: 256204 | AF70: 0.0412 | AG70: 18.68
A71: Location 69 | B71: 87736 | C71: 0.4691 | D71: 0.5309 | E71: 0 | F71: 77117 | G71: 10619 | H71: 21434 | I71: 66302 | J71: 0.6255 | K71: 0.0437 | L71: 0.0127 | M71: 0.0665 | N71: 0.2051 | O71: 0.0465 | P71: 0.4019 | Q71: 0.0231 | R71: 5.66 | S71: 923298 | T71: 0.0516 | U71: 36.04 | V71: 291439 | W71: 0.0357 | X71: 16.44 | Y71: 82524 | Z71: 0.0183 | AA71: 9.07 | AB71: 20779 | AC71: 0.0034 | AD71: 12.25 | AE71: 422754 | AF71: 0.0668 | AG71: 12.74
A72: Location 70 | B72: 86343 | C72: 0.8665 | D72: 0 | E72: 0.1335 | F72: 85196 | G72: 1147 | H72: 32540 | I72: 53803 | J72: 0.7073 | K72: 0.0132 | L72: 0.0226 | M72: 0.0606 | N72: 0.1702 | O72: 0.026 | P72: 0.444 | Q72: 0.0319 | R72: 3.73 | S72: 945387 | T72: 0.0741 | U72: 39.64 | V72: 216655 | W72: 0.0351 | X72: 19.18 | Y72: 97324 | Z72: 0.0325 | AA72: 9.31 | AB72: 8071 | AC72: 0.002 | AD72: 12.39 | AE72: 210326 | AF72: 0.0475 | AG72: 13.76
A73: Location 71 | B73: 84224 | C73: 0.468 | D73: 0.4465 | E73: 0.0855 | F73: 82941 | G73: 1283 | H73: 23602 | I73: 60622 | J73: 0.696 | K73: 0.0595 | L73: 0.0226 | M73: 0.0457 | N73: 0.1364 | O73: 0.0398 | P73: 0.3912 | Q73: 0.0371 | R73: 3.81 | S73: 1299411 | T73: 0.1228 | U73: 32.99 | V73: 294977 | W73: 0.0548 | X73: 16.79 | Y73: 99905 | Z73: 0.0328 | AA73: 9.48 | AB73: 498229 | AC73: 0.1148 | AD73: 13.54 | AE73: 261306 | AF73: 0.0417 | AG73: 19.56
A74: Location 72 | B74: 80454 | C74: 0.4812 | D74: 0.4878 | E74: 0.031 | F74: 78172 | G74: 2282 | H74: 23689 | I74: 56765 | J74: 0.6863 | K74: 0.0102 | L74: 0.0251 | M74: 0.0516 | N74: 0.1798 | O74: 0.0471 | P74: 0.3792 | Q74: 0.0161 | R74: 3.9 | S74: 968430 | T74: 0.0829 | U74: 37.21 | V74: 263468 | W74: 0.0396 | X74: 21.17 | Y74: 74417 | Z74: 0.0257 | AA74: 9.22 | AB74: 3862 | AC74: 0.0005 | AD74: 24.71 | AE74: 389537 | AF74: 0.109 | AG74: 11.39
A75: Location 73 | B75: 78872 | C75: 0.5632 | D75: 0.3955 | E75: 0.0413 | F75: 77376 | G75: 1496 | H75: 34778 | I75: 44094 | J75: 0.6911 | K75: 0.0089 | L75: 0.0219 | M75: 0.0645 | N75: 0.1633 | O75: 0.0503 | P75: 0.4543 | Q75: 0.0211 | R75: 3.96 | S75: 752110 | T75: 0.0677 | U75: 35.57 | V75: 179684 | W75: 0.0286 | X75: 20.1 | Y75: 61698 | Z75: 0.0219 | AA75: 9.04 | AB75: 57203 | AC75: 0.0168 | AD75: 10.91 | AE75: 173375 | AF75: 0.0384 | AG75: 14.46
A76: Location 74 | B76: 77007 | C76: 0.4573 | D76: 0.5427 | E76: 0 | F76: 76348 | G76: 659 | H76: 18371 | I76: 58636 | J76: 0.6952 | K76: 0.0088 | L76: 0.0218 | M76: 0.0461 | N76: 0.1914 | O76: 0.0367 | P76: 0.3477 | Q76: 0.0356 | R76: 5.24 | S76: 1347620 | T76: 0.1014 | U76: 32.91 | V76: 322597 | W76: 0.0448 | X76: 17.84 | Y76: 225764 | Z76: 0.0621 | AA76: 9 | AB76: 442361 | AC76: 0.0809 | AD76: 13.54 | AE76: 507994 | AF76: 0.1181 | AG76: 10.65
A77: Location 75 | B77: 76133 | C77: 0.9911 | D77: 0 | E77: 0.0089 | F77: 74144 | G77: 1989 | H77: 38925 | I77: 37208 | J77: 0.7442 | K77: 0.0091 | L77: 0.0186 | M77: 0.0417 | N77: 0.1538 | O77: 0.0325 | P77: 0.5518 | Q77: 0.0555 | R77: 3.79 | S77: 794500 | T77: 0.0762 | U77: 36.13 | V77: 216738 | W77: 0.0358 | X77: 20.99 | Y77: 60964 | Z77: 0.0233 | AA77: 9.06 | AB77: 667 | AC77: 0.0001 | AD77: 24.05 | AE77: 149452 | AF77: 0.0409 | AG77: 12.66
A78: Location 76 | B78: 75740 | C78: 0.4628 | D78: 0.5372 | E78: 0 | F78: 74489 | G78: 1251 | H78: 22442 | I78: 53298 | J78: 0.7082 | K78: 0.0015 | L78: 0.0291 | M78: 0.0498 | N78: 0.1747 | O78: 0.0366 | P78: 0.3633 | Q78: 0.0258 | R78: 4.11 | S78: 1101447 | T78: 0.0931 | U78: 38.02 | V78: 177483 | W78: 0.0366 | X78: 15.59 | Y78: 71829 | Z78: 0.0252 | AA78: 9.16 | AB78: 4229 | AC78: 0.0012 | AD78: 11.24 | AE78: 214640 | AF78: 0.0425 | AG78: 16.24
A79: Location 77 | B79: 75671 | C79: 0.4313 | D79: 0.5416 | E79: 0.0271 | F79: 75167 | G79: 504 | H79: 23787 | I79: 51884 | J79: 0.735 | K79: 0.016 | L79: 0.0292 | M79: 0.0452 | N79: 0.1437 | O79: 0.0308 | P79: 0.3802 | Q79: 0.0488 | R79: 4.8 | S79: 667903 | T79: 0.0541 | U79: 33.94 | V79: 137412 | W79: 0.019 | X79: 19.91 | Y79: 64934 | Z79: 0.02 | AA79: 8.94 | AB79: 239095 | AC79: 0.0466 | AD79: 14.11 | AE79: 293944 | AF79: 0.0703 | AG79: 11.49
A80: Location 78 | B80: 75579 | C80: 0.4006 | D80: 0.5994 | E80: 0 | F80: 74342 | G80: 1237 | H80: 11824 | I80: 63755 | J80: 0.6419 | K80: 0.0163 | L80: 0.0413 | M80: 0.0573 | N80: 0.2045 | O80: 0.0387 | P80: 0.286 | Q80: 0.0323 | R80: 4.49 | S80: 1103652 | T80: 0.0894 | U80: 36.38 | V80: 265884 | W80: 0.0446 | X80: 17.58 | Y80: 192401 | Z80: 0.0636 | AA80: 8.91 | AB80: 13137 | AC80: 0.0014 | AD80: 26.75 | AE80: 298562 | AF80: 0.0994 | AG80: 8.85
A81: Location 79 | B81: 75312 | C81: 0.5934 | D81: 0.4066 | E81: 0 | F81: 74287 | G81: 1025 | H81: 28543 | I81: 46769 | J81: 0.6782 | K81: 0.0281 | L81: 0.0166 | M81: 0.0466 | N81: 0.1848 | O81: 0.0457 | P81: 0.449 | Q81: 0.0564 | R81: 4.07 | S81: 846849 | T81: 0.0708 | U81: 38.96 | V81: 173239 | W81: 0.0298 | X81: 18.94 | Y81: 92931 | Z81: 0.0328 | AA81: 9.23 | AB81: 48 | AC81: 0 | AD81: 27.64 | AE81: 256103 | AF81: 0.0721 | AG81: 11.58
A82: Location 80 | B82: 74838 | C82: 0.4784 | D82: 0.5216 | E82: 0 | F82: 74182 | G82: 656 | H82: 19475 | I82: 55363 | J82: 0.6915 | K82: 0.0168 | L82: 0.0362 | M82: 0.0502 | N82: 0.1642 | O82: 0.0411 | P82: 0.3704 | Q82: 0.01 | R82: 4.53 | S82: 627069 | T82: 0.1108 | U82: 16.71 | V82: 187267 | W82: 0.0291 | X82: 19.03 | Y82: 56737 | Z82: 0.0188 | AA82: 8.89 | AB82: 156796 | AC82: 0.0164 | AD82: 28.2 | AE82: 246546 | AF82: 0.0539 | AG82: 13.52
A83: Location 81 | B83: 74428 | C83: 0.5635 | D83: 0.4365 | E83: 0 | F83: 72726 | G83: 1702 | H83: 33124 | I83: 41304 | J83: 0.704 | K83: 0.0422 | L83: 0.0134 | M83: 0.0433 | N83: 0.1505 | O83: 0.0465 | P83: 0.4735 | Q83: 0.0173 | R83: 5.25 | S83: 966967 | T83: 0.0674 | U83: 36.71 | V83: 163691 | W83: 0.02 | X83: 20.95 | Y83: 72299 | Z83: 0.0209 | AA83: 8.86 | AB83: 0 | AE83: 201761 | AF83: 0.0566 | AG83: 9.12
A84: Location 82 | B84: 72050 | C84: 0.585 | D84: 0.3554 | E84: 0.0596 | F84: 70547 | G84: 1503 | H84: 29215 | I84: 42835 | J84: 0.6977 | K84: 0.0116 | L84: 0.0393 | M84: 0.0625 | N84: 0.1443 | O84: 0.0447 | P84: 0.3897 | Q84: 0.0469 | R84: 4.21 | S84: 1203209 | T84: 0.1067 | U84: 37.18 | V84: 284896 | W84: 0.0467 | X84: 20.12 | Y84: 135848 | Z84: 0.0492 | AA84: 9.1 | AB84: 11063 | AC84: 0.0029 | AD84: 12.79 | AE84: 196268 | AF84: 0.0619 | AG84: 10.46
A85: Location 83 | B85: 69188 | C85: 0.6063 | D85: 0.3488 | E85: 0.0449 | F85: 68297 | G85: 891 | H85: 28179 | I85: 41009 | J85: 0.726 | K85: 0.0298 | L85: 0.024 | M85: 0.0357 | N85: 0.1489 | O85: 0.0356 | P85: 0.4638 | Q85: 0.0371 | R85: 3.49 | S85: 988415 | T85: 0.0978 | U85: 41.83 | V85: 186258 | W85: 0.045 | X85: 17.11 | Y85: 75203 | Z85: 0.0334 | AA85: 9.3 | AB85: 229652 | AC85: 0.0765 | AD85: 12.42 | AE85: 206474 | AF85: 0.0671 | AG85: 12.73
A86: Location 84 | B86: 67995 | C86: 0.5332 | D86: 0.4668 | E86: 0 | F86: 67025 | G86: 970 | H86: 24610 | I86: 43385 | J86: 0.6954 | K86: 0.0104 | L86: 0.0164 | M86: 0.0296 | N86: 0.1913 | O86: 0.0569 | P86: 0.39 | Q86: 0.035 | R86: 4.99 | S86: 800821 | T86: 0.0589 | U86: 40.06 | V86: 173056 | W86: 0.0266 | X86: 19.19 | Y86: 44634 | Z86: 0.0145 | AA86: 9.04 | AB86: 39875 | AC86: 0.0091 | AD86: 12.93 | AE86: 214513 | AF86: 0.0598 | AG86: 10.57
A87: Location 85 | B87: 67112 | C87: 0.5307 | D87: 0.4512 | E87: 0.0181 | F87: 66152 | G87: 960 | H87: 22892 | I87: 44220 | J87: 0.6886 | K87: 0.0172 | L87: 0.0293 | M87: 0.0361 | N87: 0.183 | O87: 0.0458 | P87: 0.3949 | Q87: 0.0239 | R87: 4.05 | S87: 518665 | T87: 0.1097 | U87: 17.4 | V87: 154077 | W87: 0.0286 | X87: 19.84 | Y87: 81460 | Z87: 0.0327 | AA87: 9.17 | AB87: 91335 | AC87: 0.0126 | AD87: 26.67 | AE87: 246906 | AF87: 0.0657 | AG87: 13.83
A88: Location 86 | B88: 64672 | C88: 0.4896 | D88: 0.5104 | E88: 0 | F88: 64155 | G88: 517 | H88: 21251 | I88: 43421 | J88: 0.6655 | K88: 0.0064 | L88: 0.0164 | M88: 0.0225 | N88: 0.208 | O88: 0.0812 | P88: 0.3465 | Q88: 0.0659 | R88: 5.25 | S88: 988755 | T88: 0.0764 | U88: 38.09 | V88: 459039 | W88: 0.0723 | X88: 18.7 | Y88: 180663 | Z88: 0.0587 | AA88: 9.07 | AB88: 161705 | AC88: 0.0375 | AD88: 12.69 | AE88: 572644 | AF88: 0.2068 | AG88: 8.15
A89: Location 87 | B89: 60837 | C89: 0.4282 | D89: 0.5142 | E89: 0.0576 | F89: 60330 | G89: 507 | H89: 14519 | I89: 46318 | J89: 0.6562 | K89: 0.0544 | L89: 0.0383 | M89: 0.0697 | N89: 0.1419 | O89: 0.0395 | P89: 0.3188 | Q89: 0.0254 | R89: 4.19 | S89: 818563 | T89: 0.0992 | U89: 32.36 | V89: 243897 | W89: 0.0578 | X89: 16.55 | Y89: 72198 | Z89: 0.0314 | AA89: 9.02 | AB89: 15758 | AC89: 0.0052 | AD89: 11.98 | AE89: 174069 | AF89: 0.0394 | AG89: 17.34
A90: Location 88 | B90: 60573 | C90: 0.512 | D90: 0.488 | E90: 0 | F90: 59947 | G90: 626 | H90: 15577 | I90: 44996 | J90: 0.6463 | K90: 0.0723 | L90: 0.0209 | M90: 0.044 | N90: 0.1629 | O90: 0.0537 | P90: 0.3792 | Q90: 0.0296 | R90: 3.82 | S90: 889578 | T90: 0.1146 | U90: 33.58 | V90: 216849 | W90: 0.0557 | X90: 16.84 | Y90: 68337 | Z90: 0.0314 | AA90: 9.4 | AB90: 55598 | AC90: 0.0183 | AD90: 13.14 | AE90: 129890 | AF90: 0.0312 | AG90: 18.03
A91: Location 89 | B91: 60464 | C91: 0.4239 | D91: 0.5761 | E91: 0 | F91: 58763 | G91: 1701 | H91: 8017 | I91: 52447 | J91: 0.5956 | K91: 0.0423 | L91: 0.0148 | M91: 0.0602 | N91: 0.2034 | O91: 0.0837 | P91: 0.2608 | Q91: 0.0433 | R91: 4.8 | S91: 810564 | T91: 0.07 | U91: 39.85 | V91: 264055 | W91: 0.0487 | X91: 18.65 | Y91: 35845 | Z91: 0.014 | AA91: 8.82 | AB91: 792705 | AC91: 0.217 | AD91: 12.58 | AE91: 276559 | AF91: 0.098 | AG91: 9.72
A92: Location 90 | B92: 60208 | C92: 0.5199 | D92: 0.4801 | E92: 0 | F92: 59374 | G92: 834 | H92: 18163 | I92: 42045 | J92: 0.6883 | K92: 0.0173 | L92: 0.0212 | M92: 0.0338 | N92: 0.1918 | O92: 0.0476 | P92: 0.3751 | Q92: 0.0375 | R92: 4.17 | S92: 595350 | T92: 0.1386 | U92: 17.09 | V92: 132037 | W92: 0.0265 | X92: 19.81 | Y92: 55708 | Z92: 0.0245 | AA92: 9.06 | AB92: 193896 | AC92: 0.0306 | AD92: 25.22 | AE92: 176141 | AF92: 0.0552 | AG92: 12.69
A93: Location 91 | B93: 58761 | C93: 0.5812 | D93: 0.4188 | E93: 0 | F93: 57464 | G93: 1297 | H93: 24661 | I93: 34100 | J93: 0.7824 | K93: 0.0061 | L93: 0.0101 | M93: 0.0426 | N93: 0.1309 | O93: 0.0279 | P93: 0.4382 | Q93: 0.0388 | R93: 3.75 | S93: 636491 | T93: 0.0779 | U93: 37.05 | V93: 132599 | W93: 0.0305 | X93: 19.73 | Y93: 41270 | Z93: 0.0204 | AA93: 9.17 | AB93: 921 | AC93: 0.0002 | AD93: 20.11 | AE93: 148001 | AF93: 0.0576 | AG93: 11.65
A94: Location 92 | B94: 57293 | C94: 0.5418 | D94: 0.3816 | E94: 0.0766 | F94: 56466 | G94: 827 | H94: 21186 | I94: 36107 | J94: 0.7169 | K94: 0.015 | L94: 0.015 | M94: 0.0418 | N94: 0.1746 | O94: 0.0367 | P94: 0.3851 | Q94: 0.0228 | R94: 3.51 | S94: 613015 | T94: 0.0736 | U94: 41.38 | V94: 190736 | W94: 0.0522 | X94: 18.16 | Y94: 72758 | Z94: 0.0384 | AA94: 9.41 | AB94: 11714 | AC94: 0.0048 | AD94: 12.13 | AE94: 161123 | AF94: 0.0613 | AG94: 13.06
A95: Location 93 | B95: 57140 | C95: 0.5291 | D95: 0.4709 | E95: 0 | F95: 56013 | G95: 1127 | H95: 20698 | I95: 36442 | J95: 0.7047 | K95: 0.0165 | L95: 0.0324 | M95: 0.0491 | N95: 0.1506 | O95: 0.0468 | P95: 0.3862 | Q95: 0.0246 | R95: 4.56 | S95: 590093 | T95: 0.0678 | U95: 33.4 | V95: 140352 | W95: 0.0302 | X95: 17.81 | Y95: 57819 | Z95: 0.0253 | AA95: 8.77 | AB95: 0 | AE95: 161299 | AF95: 0.0561 | AG95: 11.03
A96: Location 94 | B96: 54926 | C96: 0.4697 | D96: 0.5303 | E96: 0 | F96: 54533 | G96: 393 | H96: 20608 | I96: 34318 | J96: 0.6954 | K96: 0.0196 | L96: 0.0248 | M96: 0.0442 | N96: 0.1839 | O96: 0.0322 | P96: 0.369 | Q96: 0.0474 | R96: 4.31 | S96: 771900 | T96: 0.0802 | U96: 40.62 | V96: 118520 | W96: 0.0225 | X96: 22.19 | Y96: 51853 | Z96: 0.024 | AA96: 9.11 | AB96: 22828 | AC96: 0.0076 | AD96: 12.62 | AE96: 100203 | AF96: 0.036 | AG96: 11.76
A97: Location 95 | B97: 53491 | C97: 0.7025 | D97: 0.2975 | E97: 0 | F97: 52749 | G97: 742 | H97: 31834 | I97: 21657 | J97: 0.8263 | K97: 0.01 | L97: 0.0115 | M97: 0.0304 | N97: 0.0982 | O97: 0.0237 | P97: 0.5634 | Q97: 0.0251 | R97: 3.49 | S97: 364133 | T97: 0.069 | U97: 28.28 | V97: 118966 | W97: 0.0325 | X97: 19.62 | Y97: 7466 | Z97: 0.0044 | AA97: 9.02 | AB97: 0 | AE97: 136153 | AF97: 0.0668 | AG97: 10.93
A98: Location 96 | B98: 50248 | C98: 0.5492 | D98: 0.4508 | E98: 0 | F98: 49392 | G98: 856 | H98: 18329 | I98: 31919 | J98: 0.7436 | K98: 0.0119 | L98: 0.03 | M98: 0.0436 | N98: 0.1423 | O98: 0.0287 | P98: 0.4108 | Q98: 0.0464 | R98: 3.93 | S98: 386999 | T98: 0.0558 | U98: 35.16 | V98: 106933 | W98: 0.0258 | X98: 21 | Y98: 29018 | Z98: 0.0166 | AA98: 8.88 | AB98: 22048 | AC98: 0.0091 | AD98: 12.27 | AE98: 135540 | AF98: 0.0506 | AG98: 13.57
A99: Location 97 | B99: 48189 | C99: 0.4987 | D99: 0.5013 | E99: 0 | F99: 47819 | G99: 370 | H99: 13688 | I99: 34501 | J99: 0.6027 | K99: 0.0106 | L99: 0.0205 | M99: 0.0429 | N99: 0.2402 | O99: 0.0832 | P99: 0.3564 | Q99: 0.0816 | R99: 5.18 | S99: 793024 | T99: 0.0806 | U99: 39.4 | V99: 194724 | W99: 0.0413 | X99: 18.87 | Y99: 75702 | Z99: 0.0334 | AA99: 9.08 | AB99: 19391 | AC99: 0.0059 | AD99: 13.07 | AE99: 384436 | AF99: 0.1599 | AG99: 9.63
A100: Location 98 | B100: 46693 | C100: 0.3046 | D100: 0.6633 | E100: 0.0321 | F100: 45945 | G100: 748 | H100: 4463 | I100: 42230 | J100: 0.6978 | K100: 0.0067 | L100: 0.0178 | M100: 0.0379 | N100: 0.1747 | O100: 0.065 | P100: 0.2268 | Q100: 0.0176 | R100: 5.44 | S100: 754479 | T100: 0.078 | U100: 38.05 | V100: 341285 | W100: 0.0728 | X100: 18.44 | Y100: 184826 | Z100: 0.0837 | AA100: 8.68 | AB100: 227071 | AC100: 0.0739 | AD100: 12.08 | AE100: 127443 | AF100: 0.0593 | AG100: 8.45
A101: Location 99 | B101: 45969 | C101: 0.3739 | D101: 0.6261 | E101: 0 | F101: 44926 | G101: 1043 | H101: 6352 | I101: 39617 | J101: 0.6378 | K101: 0.0077 | L101: 0.0132 | M101: 0.0392 | N101: 0.2294 | O101: 0.0726 | P101: 0.2379 | Q101: 0.029 | R101: 4.92 | S101: 917977 | T101: 0.0981 | U101: 41.36 | V101: 209310 | W101: 0.0496 | X101: 18.67 | Y101: 26392 | Z101: 0.0135 | AA101: 8.67 | AB101: 364855 | AC101: 0.1298 | AD101: 12.43 | AE101: 108148 | AF101: 0.0508 | AG101: 9.41
A102: Location 100 | B102: 45560 | C102: 0.975 | D102: 0 | E102: 0.025 | F102: 44858 | G102: 702 | H102: 20782 | I102: 24778 | J102: 0.7548 | K102: 0.0012 | L102: 0.0043 | M102: 0.0376 | N102: 0.1681 | O102: 0.034 | P102: 0.5391 | Q102: 0.0265 | R102: 3.6 | S102: 334977 | T102: 0.0749 | U102: 27.3 | V102: 96759 | W102: 0.0301 | X102: 19.59 | Y102: 29577 | Z102: 0.0198 | AA102: 9.11 | AB102: 108 | AC102: 0.0001 | AD102: 10.78 | AE102: 124587 | AF102: 0.0503 | AG102: 15.13
A103: Location 101 | B103: 44973 | C103: 0.5913 | D103: 0.4087 | E103: 0 | F103: 44191 | G103: 782 | H103: 19391 | I103: 25582 | J103: 0.77 | K103: 0 | L103: 0.0244 | M103: 0.0525 | N103: 0.1249 | O103: 0.0281 | P103: 0.4615 | Q103: 0.0116 | R103: 3.27 | S103: 355917 | T103: 0.0616 | U103: 39.26 | V103: 91624 | W103: 0.0322 | X103: 19.3 | Y103: 17923 | Z103: 0.0131 | AA103: 9.29 | AB103: 0 | AE103: 96605 | AF103: 0.0546 | AG103: 12.01
A104: Location 102 | B104: 43854 | C104: 0.3329 | D104: 0.5966 | E104: 0.0705 | F104: 41501 | G104: 2353 | H104: 10170 | I104: 33684 | J104: 0.6608 | K104: 0.0001 | L104: 0.0829 | M104: 0.0516 | N104: 0.1413 | O104: 0.0633 | P104: 0.2965 | Q104: 0.0506 | R104: 2.83 | S104: 531342 | T104: 0.1194 | U104: 35.8 | V104: 81711 | W104: 0.039 | X104: 16.88 | Y104: 81045 | Z104: 0.0649 | AA104: 10.04 | AB104: 0 | AE104: 28939 | AF104: 0.01 | AG104: 23.35
A105: Location 103 | B105: 42734 | C105: 0.5834 | D105: 0.4166 | E105: 0 | F105: 42145 | G105: 589 | H105: 19486 | I105: 23248 | J105: 0.7357 | K105: 0.0285 | L105: 0.0176 | M105: 0.0391 | N105: 0.1481 | O105: 0.031 | P105: 0.4497 | Q105: 0.0225 | R105: 4 | S105: 433516 | T105: 0.0609 | U105: 41.63 | V105: 95327 | W105: 0.0291 | X105: 19.16 | Y105: 60528 | Z105: 0.0384 | AA105: 9.2 | AB105: 14282 | AC105: 0.0048 | AD105: 17.45 | AE105: 84223 | AF105: 0.0431 | AG105: 11.43
A106: Location 104 | B106: 42390 | C106: 0.7634 | D106: 0.2366 | E106: 0 | F106: 41381 | G106: 1009 | H106: 22141 | I106: 20249 | J106: 0.6926 | K106: 0.0002 | L106: 0.0586 | M106: 0.0221 | N106: 0.209 | O106: 0.0175 | P106: 0.4971 | Q106: 0.0508 | R106: 3.45 | S106: 616460 | T106: 0.0998 | U106: 42.22 | V106: 166853 | W106: 0.0531 | X106: 21.49 | Y106: 51177 | Z106: 0.0384 | AA106: 9.11 | AB106: 8677 | AC106: 0.0044 | AD106: 13.49 | AE106: 89351 | AF106: 0.0424 | AG106: 14.39
A107: Location 105 | B107: 41243 | C107: 0.5099 | D107: 0.4901 | E107: 0 | F107: 37399 | G107: 3844 | H107: 15376 | I107: 25867 | J107: 0.7025 | K107: 0.0422 | L107: 0.0144 | M107: 0.0494 | N107: 0.1376 | O107: 0.0539 | P107: 0.4111 | Q107: 0.0272 | R107: 4.56 | S107: 324772 | T107: 0.041 | U107: 42.17 | V107: 87269 | W107: 0.0247 | X107: 18.8 | Y107: 22745 | Z107: 0.0141 | AA107: 8.61 | AB107: 149488 | AC107: 0.0646 | AD107: 12.3 | AE107: 126094 | AF107: 0.0891 | AG107: 7.53
A108: Location 106 | B108: 38747 | C108: 0.5717 | D108: 0.4283 | E108: 0 | F108: 38373 | G108: 374 | H108: 13773 | I108: 24974 | J108: 0.722 | K108: 0.0705 | L108: 0.0188 | M108: 0.0503 | N108: 0.1192 | O108: 0.0192 | P108: 0.4314 | Q108: 0.0407 | R108: 4.3 | S108: 529319 | T108: 0.0959 | U108: 33.14 | V108: 162838 | W108: 0.0596 | X108: 16.4 | Y108: 26109 | Z108: 0.0175 | AA108: 8.94 | AB108: 9363 | AC108: 0.0044 | AD108: 12.87 | AE108: 128464 | AF108: 0.0479 | AG108: 16.1
A109: Location 107 | B109: 38031 | C109: 0.5228 | D109: 0.4772 | E109: 0 | F109: 37701 | G109: 330 | H109: 9594 | I109: 28437 | J109: 0.7234 | K109: 0.0058 | L109: 0.0341 | M109: 0.043 | N109: 0.1563 | O109: 0.0374 | P109: 0.3895 | Q109: 0.0161 | R109: 4.35 | S109: 340069 | T109: 0.1322 | U109: 15.56 | V109: 77991 | W109: 0.0242 | X109: 19.46 | Y109: 31621 | Z109: 0.0222 | AA109: 8.61 | AB109: 63884 | AC109: 0.0172 | AD109: 22.5 | AE109: 139228 | AF109: 0.0627 | AG109: 13.43
A110: Location 108 | B110: 37060 | C110: 0.9628 | D110: 0 | E110: 0.0372 | F110: 36018 | G110: 1042 | H110: 21004 | I110: 16056 | J110: 0.7931 | K110: 0.0001 | L110: 0.0023 | M110: 0.0334 | N110: 0.1439 | O110: 0.0271 | P110: 0.5655 | Q110: 0.0816 | R110: 4.09 | S110: 580257 | T110: 0.1057 | U110: 36.21 | V110: 149696 | W110: 0.0515 | X110: 19.2 | Y110: 54395 | Z110: 0.0399 | AA110: 9 | AB110: 54439 | AC110: 0.0264 | AD110: 13.59 | AE110: 58723 | AF110: 0.0326 | AG110: 11.87
...
